Workbook

Sheet REKAP
A1: NO | B1: TANGGAL | C1: MEDIA ADUAN | D1: NAMA / NOMOR | E1: JENIS | F1: SUBDIT | G1: PERTANYAAN | H1: JAWABAN
A2: 1 | B2: 45422 | C2: WHATSAPP | D2: 62 857-3004-2502 | E2: SAMSAT | F2: REGIDENT | G2: - Selamat pagi Bapak/Ibu, saya Rizki dari Surabaya, mohon izin bertanya/info, untuk pengurusan kartu induk BPKB yang hilang perlu waktu berapa lama ya? Atau adakah nomor/media/kanal yang bisa dihubungi untuk bertanya karena saya cari melalui internet/medsos sepertinya belum ada? Mohon bantuannya bapak/ibu. Terimakasih🙏🏻🙏🏻 | H2: - bisa dibantu nopolnya? kami bantu cek
A3: 2 | B3: 45426 | C3: WHATSAPP | D3: 62 822-4555-4323 | E3: LAIN-LAIN | G3: - Assalamualaikum pak selamat siang - Saya mau ngambil stnk tanpa harus di sidang gimana caranya? - Ini tandanya polsek gubeng, Tapi malah di suruh sidang di Sukomanunggal. - Katanya bapak nya saya di suruh (ngurus atau disidang) Nah saya pilih di urus pak biar cepat dan clear. | H3: - walaikumsalam selamat siang - ada yg bisa kami bantu - Wilayah mana pak/bu - ada no tilangnya kita bantu cek terlebih dahulu - silahkan datang di satpas colombo untuk meminta kode briva di kantor tilang polrestabes surabaya
A4: 3 | B4: 45428 | C4: WHATSAPP | D4: +62 856-5582-1443 | E4: SAMSAT | G4: -Selamat pagi -Perkenalkan saya Herlambang, -Mohon bantuan petunjuknya Bapak/Ibu, untuk persyaratan penerbitan Surat Rekomendasi Polda Jatim, untuk keperluan pendaftaran STNK & BPKB kendaraan di kantor Samsat daerah Jawa Timur. -Domisili Banyuwangi Pak -Namun saat ini kendaraan berada di Bekasi, Jawa Barat Pak/Bu -Baik terimakasih atas informasinya, Izin bertanya apakah persyaratan penerbitan Surat Rekomendasi bisa disampaikan melalui jasa pengiriman dokumen (Pos) atau melalui email Pak/Bu?- -Karena saat ini saya tinggal di bekasi namun data KTP masih beralamat di Banyuwangi. Terimakasih🙏 -Baik Bapak/Ibu terimakasih atas informasinya🙏 -Sehubungan dengan persyaratan yang dimohonkan untuk penerbitan surat Rekomendasi Polda Jatim, ada persamaan berkas yang disampaikan untuk penerbitan BPKB dari kantor Samsat Banyuwangi sesuai persyaratan terlampir Pak/Bu -Mohon izin bertanya kembali Pak/bu apakah ketika pengajuan permohonan penerbitan surat rekomendasi Polda Jatim Dokumen Asli hanya untuk ditunjukkan dan yang disampaikan untuk surat rekomendasi adalah dokumen duplikat/copy Bapak/Ibu? | H4: -pemenang lelang domisili mana pak/bu -atau bisa difotokan dokumen lelalng nya -mohon maaf tidak bisa, dikarenakan butuh berkas asli, dan apabila dikirim melalui POS dikhawatirkan tidak terkirim, trims -Untuk surat yg dibawa ke polda harus asli pak/bu
A5: 5 | B5: 45437 | C5: FACEBOOK | D5: Sloow Broow | E5: SAMSAT | G5: Untuk Sidoarjo dimana aja untuk bayar pajak spdh | H5: silahkan datang di samsat corner lotte mart,samsat keliling kota,samsat keliling krian, samsat payment point wadung asri,samsat payment point samsat lama,samsat payment point bank jatim taman, samsat payment point puspa agro terima kasih
A6: 6 | B6: 45438 | C6: FACEBOOK | D6: Anjam Unyil | E6: SAMSAT | G6: 1. Bayar pajak kendaraan tanpa ktp pemilik pertama apakah bisa??? 2.Siap 🙏🙏🙏 | H6: mohon maaf tidak bisa, apabila sudah berpindah tangan bisa balik nama di samsat asal, terima kasih
A7: 4 | B7: 45439 | C7: WHATSAPP | D7: +62 822-3061-6978 | E7: LAIN-LAIN | G7: -Selamat siang, betul dengan akun whatsapp polsek tegalsari surabaya? -Mohon maaf, adakah kontak whatsapp polsek tegalsari yang bisa saya hubungi Pak/Bu? -Saya ingin menanyakan perihal kerabat saya yg terakhir kali infonya sedang berada di polsek tegalsari Surabaya🙏🏻- -Baik, terimakasih bantuannya Pak/Bu 🙏🏻 -Baik, untuk nomor whatsapp nya belum ada ya Pak/Bu? | H7: -dengan rtmc polda jatim -Ada yg bisa dibantu -Mhn waktu -izin pak/bu ini untuk nomor dari polsek tegal sari 031 5341052 -untuk sementara nomor dari polsek tegalsari hanya ini saja
A8: 7 | B8: 45439 | C8: FACEBOOK | D8: Airin Dan Aura | E8: SIM | G8: Maaf, bs untuk upgrade SIM A ke B1 | H8: mohon maaf tidak bisa sim keliling hanya melayani perpanjangan sim A dan C saja, terima kasih
A9: 8 | B9: 45440 | C9: FACEBOOK | D9: Eko Anis M | E9: SIM | G9: 1. Kalau perpanjang SIM maksimal berapa hari sebelum masa berlaku 2. ini berlaku seluruh Jawa timur | H9: 1. sebelum masa berlaku habis 2. iya pak
A10: 1 | B10: 45449 | C10: FACEBOOK | D10: Tulus Machfudi | E10: SIM | F10: REGIDENT | G10: 1. SIM saya surabaya, sekarang KTP Sidoarjo. Mau memperpanjang SIM. Mohon pencerahan dari ditlantas Polda. Terima kasih. 2.Terima kasih pencerahannya. | H10: 1. kalau SIM A dan C bisa diperpanjang dimana saja mas, asal SIM tersebut belum kadaluarsa dan mengikuti KTP alamat baru
A11: 2 | B11: 45449 | C11: FACEBOOK | D11: Irosab | E11: SIM | G11: 1. Apakah di sim keliling di sediakan tempat psikologi dan surat kesehatan | H11: 1. sudah tersedia
A12: 3 | B12: 45449 | C12: FACEBOOK | D12: Hayik Depp | E12: SAMSAT | G12: 1. mutasi masuk apakah bisa langsung ke samsat tujuan? 2. mobil plat N Malang masuk ke Surabaya samsat Kedung Cowek dan mobil plat Bandar Lampung masuk ke Surabaya samsat Kedung Cowek ndan, mohon pencerahannya, terima kasih 3.sudah tidak perlu cabut berkas lagi di samsat asal ya ndan? 4. siap, terima kasih infonya ndan 🙏🙏🙏 | H12: 1.dari samsat mana kemana pak 2. apabila dari plat N langsung ke samsat tujuan namun untuk plat luar wilayah jawa timur ke polda terlebih dahulu, trims 3. tetap cabut di samsat asal pak
A13: 4 | B13: 45449 | C13: FACEBOOK | D13: Taufiq Cholis | E13: SIM | G13: 1. Perpanjang SIM a/c bulan 10 matinya , dan diperpanjang bulan 6 sekarang apa bisa 2. siap terima kasih | H13: 1. bisa pak, dan masa berlaku mengikuti tgl pendaftaran perpanjangan SIM 2. terima kasih kembali
A14: 5 | B14: 45449 | C14: FACEBOOK | D14: Heryanto Frizka | E14: SAMSAT | G14: 1. Surabaya pusat dimana yg terdekat 2. makasih infonya | H14: 1. bisa di samsat payment point taman budaya cak durasim 2. terima kasih kembali
A15: 6 | B15: 45449 | C15: FACEBOOK | D15: Agung Wida Ngalam Greasetrap | E15: SAMSAT | G15: 1. Untuk PAJAK RanMor 5th an/ sekalian MUTASI luar kota bisa? Klu tidak bisa,..Samsat Tandes Besok Sabtu tgl 8 pa buka? 2. thanks infonya | H15: 1.samsat keliling hanya melayani pembayaran dan pengesahan pajak tahunan, hari sabtu buka mulai pukul 08.00 - 11.00 WIB, trims 2. terima kasih kembali
A16: 7 | B16: 45449 | C16: FACEBOOK | D16: Kendiel Joko | E16: SIM | G16: 1. Blitar gak pernah ada 2. sim keliling ye | H16: 1. blitar kab hari ini 7 Juni 2024 ada di Halaman Kec Gandusari dan besok 8 Juni 2024 ada di Halam Kantor Kec Garum
A17: 8 | B17: 45449 | C17: FACEBOOK | D17: Febrina Prameswari | E17: SIM | G17: 1. Utk SIM keliling di Sidoarjo apakah memakai kuota? Per hari berapa kuota? Mohon info 2. baik Terimakasih infonya karena suami pernah datang ditolak alasannya kuotanya habis pdhl belum jam 12 siang. | H17: 1. tanpa kuota,mbak
A18: 9 | B18: 45449 | C18: WHATSAPP | D18: +62 818-578-481 | E18: SAMSAT | G18: 1.Selamat pagi Mohon info untuk pengurusan kendaraan baru dari dealer, syarat pengurusannya apa aja? Dan apa kendaraannya perlu dibawa ke polda? | H18: 1. selamat pagi, surat faktur ktp dan kendaraan nya dibawa ke polda
A19: 10 | B19: 45449 | C19: WHATSAPP | D19: +62 899-3422-813 | E19: SAMSAT | G19: 1. Siang pak 2. Maaf. Apakah bisa tanya untuk stnk sama BPKB motor saya yang kemarin bulan januari balik nama. Apakah sudah selesai apa belum pak?? 3. nopol S 3812 TU 4. iya pak 5. Siang pak | H19: 1. siang 2. sebentar ya pak saya bantu cekkan 3. sudah selesai pak dan sudah diambil 4. kendaraan atas nama AKMAD SUHADI
A20: 11 | B20: 45451 | C20: WHATSAPP | D20: 62 896-7875-0699 | E20: LAIN-LAIN | G20: 1. Selamat siang, Mau tanya untuk jam operasional ditlantas polda jatim jam berapa sampai jam berapa ya? 2. Terimakasih | H20: 1. jam 08.00 - 12.00 ya pak/bu
A21: 12 | B21: 45451 | C21: WHATSAPP | D21: +62 823-3565-2495 | E21: SAMSAT | G21: 1. Selamat malam 2. Mohon maaf mau menanyakan untuk bpkb setelah pergantian plat kira2 bisa di ambil kapan ya ? 3. Dengan kendaraan nopol S 6985 SM 4. Mojokerto Kota 5. Oh yasudah terima kasih respon nya 6. Ohya terima kasih infonya. Berarti belum bisa diambil yaa | H21: 1. untuk pergatian platnya berada di samsat mana ya pak/bu ? 2. bisa langsung ditanyakan ke pihak terkait ya pak, di samsat mojokerto kotanya 3. setelah kita bantu cek bpkb belum tercetak atas nama TANYA EDI SAPUTRI
A22: 13 | B22: 45453 | C22: FACEBOOK | D22: Taufik | E22: SIM | G22: 1. SIM keliling gresik kok gak ada 2. Siap | H22: 1. mhn maaf masih blm beroperasi
... A41: 32 | B41: 45455 | C41: FACEBOOK | D41: Kiyomizu Kudo | E41: SIM | G41: 1. Saran sih Pak, di post nya semingu/ 3 hari sebelum hari H, biar bisa prepare cuti kerja dll... Thanks Pak | H41: 1. terima kasih sarannya
A42: 1 | B42: 45474 | C42: FACEBOOK | D42: Susanto | E42: SIM | F42: REGIDENT | G42: 1. Luar kota bisa ta pak | H42: 1. Bisa untuk Sim A & C
A43: 2 | B43: 45477 | C43: WHATSAPP | D43: +62 895-0808-4107 | E43: SIM | F43: REGIDENT | G43: 1. Sekarang jadwal yg pasti dimana pak sim kelilingnya | H43: 1. Di lippo/ramayana krian/pondok tjandra sidoarjo
A44: 3 | B44: 45478 | C44: FACEBOOK | D44: Fahri Khusaini | E44: SIM | F44: REGIDENT | G44: 1. Apakah jadwal ini berlaku sampai besok | H44: 1. untuk jadwal kami hadir tiap hari
A45: 4 | B45: 45480 | C45: WHATSAPP | D45: +62 896-7927-2792 | E45: SIM | F45: REGIDENT | G45: 1. untuk besok senin sim keliling dimana ya pak? 2. Untuk wilayah sidoarjo 3. Dari jam berapa pak? 4. Terimksh pak | H45: 1. pondok candra dan parkir lippo mall kak 2. pkl 08.00 - 12.00
A46: 5 | B46: 45481 | C46: WHATSAPP | D46: +62 819-9955-6408 | E46: SIM | F46: REGIDENT | G46: 1. Min mau tanya, besok perpanjang sim di pondok candra buka apa tidak ya? | H46: 1. buka kak 2. pkkl 08.00 - 12.00
A47: 6 | B47: 45481 | C47: WHATSAPP | D47: +62 878-5955-8191 | E47: SIM | F47: REGIDENT | G47: 1. Selamat pagi, apakah hari ini ada jadwal sim keliling di ramayana krian sidoarjo ? Terima kasih | H47: 1. pagi mas 2. ada sampai dengan pkl 12.00
A48: 7 | B48: 45481 | C48: FACEBOOK | D48: Fahri Khusaini | E48: SIM | F48: REGIDENT | G48: 1. Untuk kuota maksimal brp | H48: 1. tidak ada kuota maksimal ya pak, tapi disarankan untuk datang lebih awal
A49: 8 | B49: 45481 | C49: FACEBOOK | D49: Wahyu Prasetyo | E49: SIM | F49: REGIDENT | G49: 1. Surabaya apa bisa ndan | H49: 1. bisa
A50: 9 | B50: 45486 | C50: WHATSAPP | D50: +62 811-3237-513 | E50: SIM | F50: REGIDENT | G50: 1. Selamat malam 2. Mohon informasi untuk tes kesehatan dan psikologi utk perpanjangan SIM di Sidoarjo jika dilakukan di Mall Lippo Plaza Sidoarjo? | H50: 1. bisa kak
A51: 10 | B51: 45487 | C51: WHATSAPP | D51: +62 822-2895-8002 | E51: SIM | F51: REGIDENT | G51: 1. permisi mengenai perpanjangan sim keliling disidoarjo ada dimana untuk tanggal 15juli | H51: 1. bisa di cek di fb instagram kita ya pak
A52: 11 | B52: 45487 | C52: WHATSAPP | D52: +62 895-0932-1437 | E52: SIM | F52: REGIDENT | G52: 1. Assalamualaikum Mohon maaf.. Biaya untuk perpanjangan SIM C sekarang berapa2. Syarat perpanjangan SIM C sekarang apa saja..3. Domisili Tanggulangin Sidoarjo | H52: 1. Biaya Perpanjangan SIM C: Rp 75.000 untuk perpanjangan SIM C. Biaya Tambahan (Opsional): Surat Keterangan Sehat: Rp 25.000 - Rp 100.000 (biaya ini bervariasi tergantung pada klinik atau rumah sakit yang mengeluarkan surat keterangan sehat).
A53: 12 | B53: 45489 | C53: WHATSAPP | D53: +62 857-4876-5151 | E53: SIM | F53: REGIDENT | G53: 1. Selamat Pagi 2. Mohon info jadwal SIM keliling wilayah Sidoarjo 3. Terimakasih | H53: 1. bisa di cek di fb instagram kita ya pak
... A71: 1 | B71: 45506 | C71: WHATSAPP | D71: +62 823-3892-9663 | E71: SIM | F71: REGIDENT | G71: 1. Selamat siang, perkenalkan saya ifa, Mohon ijin, info jadwal simling Surabaya...? Terimakasih sebelumnya | H71: 1. untuk sementara masih belum ada kak, segera di update lebih lanjut
A72: 2 | B72: 45506 | C72: WHATSAPP | D72: +62 888-0487-2750 | E72: LAIN-LAIN | G72: 1. Lapor HP HILANG 2. Apakah bisa dibantu untuk menemukan | H72: 1. bisa langsung menuju ke spkt terdekat dulu pak
A73: 3 | B73: 45506 | C73: WHATSAPP | D73: +62 895-3525-65028 | E73: LAIN-LAIN | F73: LAIN-LAIN | G73: 1. Test. 2. Enggak pak,saya hanya test saja. | H73: 1. ada yang bisa dibantu?
A74: 4 | B74: 45506 | C74: WHATSAPP | D74: +62 823-3155-8693 | E74: SIM | F74: REGIDENT | G74: 1. Selamat sore pak,,, mohon ijin tanya untuk perpanjangan SIM C warga Jawa tengah di Surabaya apakah bisa dilakukan di BG junction? 2. Hari Minggu buka ya kak? 3. Terimakasih banyak kak atas infonya,,, 🙏🙏🙏 | H74: 1. bisa kak asalkan persyaratan lengkap 2. Untuk hari minggu tutup pak 3. Hari senin - sabtu buka pak
A75: 5 | B75: 45506 | C75: WHATSAPP | D75: +62 813-3646-8401 | E75: SIM | F75: REGIDENT | G75: 1. Malam...dolor jadwal sim keliling wilayah krian 2. Mohon di infoo 3. Ok makasih | H75: 1. gambar jadwal simling sidoarjo, 3 Agustus 2024
A76: 15 | B76: 45506 | C76: WHATSAPP | D76: +62 877-5168-1027 | E76: SIM | F76: REGIDENT | G76: 1. Selamat pagi 2. Apakah bisa mengurus sim pak? 3. Byar brp yh pak 4. Mau buat baru 5. Di mana yh pak 6. Ngurus nya 7. Saya Sidoarjo kec Gedangan 8. Kira" di mana yh pak ngurus buat SIM c | H76: 1. langsung saja menuju satpas terdekat 2. sim baru atau perpanjangan pak/bu 3. langsung menuju ke satpas terdekat pak/bu 4. langsung di satpas terdekat pak/bu bila di sidoarjo ada di alamat berikut Jl. Raya Cemeng Kalang No.16, Cemengkalang, Cemeng Kalang, Kec. Sidoarjo, Kabupaten Sidoarjo, Jawa Timur 61234
A77: 6 | B77: 45508 | C77: WHATSAPP | D77: +62 895-6223-21270 | E77: LAIN-LAIN | F77: GAKKUM | G77: 1. halo pak selamat pagi 2. Ini ada rame2 diduga begal kena massa, di jalan karang menur timur 3. gubeng surabaya | H77: 1. terimakasih informasinya
A78: 7 | B78: 45508 | C78: WHATSAPP | D78: +62 813-3676-6413 | E78: SIM | F78: REGIDENT | G78: 1. Jadwal SIM keliling Senin tgl 5 dimana ya untuk sidoarjo 2. apa lippo | H78: 1. barusan di upload ya pak/bu 2. gambar jadwal simling sidoarjo, 5 Agustus 2024
A79: 8 | B79: 45510 | C79: WHATSAPP | D79: +62 852-5737-7448 | E79: SIM | F79: REGIDENT | G79: 1. selamat malam 2. kalau mau ambil antrian buat besok, bagaimana caranya? | H79: 1. langsung menuju kelokasi pak/bu
A80: 9 | B80: 45510 | C80: WHATSAPP | D80: +62 856-4078-8500 | E80: SAMSAT | F80: REGIDENT | G80: 1. Selamat pagi, untuk mutasi masuk kendaraan roda 2, apakah kendaraan harus dibawa ke Polda Jatim? Sudah dilakukan cek fisik di Samsat Surabaya Barat. | H80: 1. mutasi dari daerah mana kemana ya pak?
A81: 10 | B81: 45510 | C81: WHATSAPP | D81: +62 819-4981-3288 | E81: SAMSAT | F81: REGIDENT | G81: 1. Selamat pagi pak 2. Samsat keliling di tambak sari stay sampai jam brp? 3. Halo pak 4. Ok makasih pak | H81: 1. setiap hari senin - sabtu kecuali hari jum at 08.00 - 12.00 , untuk hari jum at pukul 08.00 - 11.00
A82: 11 | B82: 45510 | C82: WHATSAPP | D82: +62 821-4085-6028 | E82: LAIN-LAIN | F82: LAIN-LAIN | G82: 1. Assalamualaikum pak 2. Barangkali nanti dijalan sekitar bratang, bapak melihat becak warna merah putih, ada tulisannya nama "Harsono", saya minta tolong kabari saya, soalnya becaknya dibawa kabur sama orang Papua 3. Siap, saya juga terimakasih | H82: 1. waalaikumsalam 2. siap bapak terimakasih informasinya
A83: 19 | B83: 45510 | C83: FACEBOOK | D83: Bayu Van Djinangun | E83: SIM | F83: REGIDENT | G83: 1. Ijin tanya pak,surat keterangan sehat,itu kita ngurus dari PUSKESMAS terdekat ya pak 2. Terima kasih pak infonya....sukses selalu buat team kerja ..... | H83: 1. bisa dari puskesmas terdekat, bisa juga langsung dilokasi pak sudah tersedia untuk cek kesehatan
A84: 20 | B84: 45510 | C84: FACEBOOK | D84: BramKenz | E84: SIM | F84: REGIDENT | G84: 1. Untuk tgl 8 Masih ada nggak 2. Itu tempatnya dimananya kalau boleh tau soalnya saya baru di sidoarjo | H84: 1. masih ada pak
... A259: 63 | B259: 45589 | C259: WHATSAPP | D259: +62 899-8932-740 | E259: SIM | F259: REGIDENT | G259: 1. Maaf mau nanya, untuk perpanjangan SIM di daerah Sidoarjo di mana saja ya, dan untuk persyaratannya apa saja, terima kasih. 2. Untuk surat kesehatan yang gimana? 3. Biasa di Pondok Chandra, ramai tidak ya? 4. Untuk biayanya kira-kira berapa ya? 5. Mau nanya saja ya kk, kalau misalnya saya urus perpanjangan SIM sebelum masa berlaku habis, apakah bisa ya? Soalnya saya baca di ulasan yang mengurus di daerah Pondok Chandra, dia mau perpanjangan SIM juga, tapi dia perpanjang sebelum masa berlaku habis, katanya ditolak, ini gimana ya kk? 6. Seminggu lagi, tapi aturan dari kepolisian kan sebelum 14 hari tidak apa-apa. | H259: 1. Untuk SIM keliling daerah Sidoarjo berada di sini pak/bu: - LIPPO PLAZA - PONDOK TJANDRA - RAMAYANA KRIAN Jam pelayanan mulai pukul 08.00 - 12.00 di hari Senin sampai hari Kamis. Bila hari Jumat dan Sabtu, jam pelayanan dimulai pukul 08.00 - 11.00 2. Pengurusan surat kesehatan sudah tersedia di tempat pak/bu. 3. Untuk PNBP SIM A perpanjangan: 80.000 Untuk PNBP SIM C perpanjangan: 75.000 CATATAN: Biaya kesehatan dan psikologi di luar PNBP Polri. 4. Mohon maaf pak, apakah masa berlaku SIM bapak masih lama atau sudah hampir mendekati masa tenggang? 5. Siap benar pak/bu. 6. Mohon maaf, besok apakah mungkin bisa dicoba lagi bapak, karena anggota SIM biasanya lebih memprioritaskan SIM yang akan habis masa berlakunya terlebih dahulu.
A260: 64 | B260: 45592 | C260: WHATSAPP | E260: SIM | F260: REGIDENT | G260: 1. Mohon maaf mau tanya: Untuk persyaratan surat sehat langsung ditempat SIM keliling atau harus ke puskesmas? 2. Baik terimakasih banyak 👍 | H260: 1. ditempat sim keliling sudah disediakan fasilitas pelayanan cek kesehatan pak/bu
A261: 1 | B261: 45599 | C261: WHATSAPP | D261: +62 813-5912-4670 | E261: SIM | F261: REGIDENT | G261: 1. Permisi mau tanya Kalo perpanjang sim offline surat keterangan sehat pakai e rikkes apa bisa? | H261: 1. kemungkinan bisa ya pak
A262: 2 | B262: 45599 | C262: WHATSAPP | D262: +62 813-8060-9364 | E262: SIM | F262: REGIDENT | G262: 1. Selamat pagi pak .untuk pelayanan pajak keliling area surabaya daerah mana ya pak.terimakasih 2. Klo ktptidk ada ditangan pertama bisa gk pak byr pjknya | H262: 1. https://www.instagram.com/p/DBdyrzUMx7Y/?utm_source=ig_web_copy_link&igsh=MzRlODBiNWFlZA== 2. tidak bisa pak/bu
A263: 3 | B263: 45599 | C263: WHATSAPP | D263: +62 856-0609-1404 | E263: SIM | F263: REGIDENT | G263: 1. selamat siang, maaf mau tanya. untuk perpanjangan SIM C keliling syaratnya apa saja ? | H263: 1. Persyaratan Perpanjangan SIM: KTP asli SIM asli Fotokopi KTP 2 lembar Fotokopi SIM 2 lembar Surat Keterangan Sehat
A264: 4 | B264: 45599 | C264: WHATSAPP | D264: +62 857-3149-3740 | E264: SIM | F264: REGIDENT | G264: 1. Selamat sore. 2. Mohon dibantu, kalau perpanjangan SIM hari Minggu besok apakah bisa? | H264: 1. Hari Minggu untuk pelayanan libur pak/bu.
A265: 5 | B265: 45600 | C265: WHATSAPP | D265: +62 812-4983-1698 | E265: SIM | F265: REGIDENT | G265: 1. Selamat siang apakah sim keliling di Sidoarjo msh ada? lokasi ny dmn sja ya? dan jam oprasionalny 2. Kalau KTP Surabaya, tetap bisa urus di sim keliling d Sidoarjo kan? 3. Lalu yg harus d bawa apa aja ya? 4. Dan tes kesehatannya itu harus bawa sendiri kah? Itu harus pemeriksaan dmn dlu ya? 5. Halo? gmn ya 6. Halo??? gmn ya 7. Utk tes kesehatan dan psikologi nya gmn ya? D sediakan atau hrus bawa sendiri? | H265: 1. Untuk Sim keliling daerah Sidoarjo berada di sini pak/bu 1. LIPPO PLAZA 2. PONDOK TJANDRA 3. RAMAYANA KRIAN Jam Pelayanan Mulai Pukul 08.00 - 12.00 di hari Senin sampai hari Kamis. Bila hari Jumat dan Sabtu, jam pelayanan dimulai pukul 08.00 - 11.00. 2. Bisa tes ditempat ya pak/bu.
A266: 6 | B266: 45600 | C266: WHATSAPP | D266: +62 813-3771-1867 | E266: SIM | F266: REGIDENT | G266: 1. Pagi kak, Mau tanya, untuk jadwal SIM keliling Daerah Pondok Tjandra apakah untuk hari ini ada kak? 2. Operasionalnya sampai jam brp kak? 3. Untuk surat sehatnya apakah di sana menyediakan kak? --- | H266: 1. Ada pak/bu. 2. 08.00 - 12.00. 3. Tersedia kak di tempat.
A267: 7 | B267: 45600 | C267: WHATSAPP | D267: +62 823-1757-6340 | E267: SIM | F267: REGIDENT | G267: 1. Selamat malam min 2. Assalamualaikum 3. Maaf menganggu pagi-pagi bapa/ibu, saya dari Sumedang mau bertanya apakah bapa/ibu pernah mendengar nama Muhammad Zaid Brata? 4. Atau tidak pun pernah menangkap 5. Okai siap makasih bapa/ibu | H267: 1. Waalaikumsalam ada yg bisa dibantu? 2. Tidak pak/bu.
A268: 8 | B268: 45600 | C268: WHATSAPP | D268: +62 838-5751-7892 | E268: SIM | F268: REGIDENT | G268: 1. Pagi kak 2. Utk perpanjangan SIM yg mati tgl 19 November 2024, Apakah pengurusan bs dilakukan pada tgl 5 - 6 November? 3. Umpama utk hari ini blm bs ya kak? | H268: 1. Bisa pak/bu. 2. Mohon waktu ya kak saya tanyakan.
A269: 9 | B269: 45600 | C269: WHATSAPP | D269: +62 852-3325-8550 | E269: SIM | F269: REGIDENT | G269: 1. Kalo sim Mati 3Hari bisa ya di urus melalui sim Keliling? | H269: 1. tidak bisa pak/bu
A270: 10 | B270: 45600 | C270: WHATSAPP | D270: +62 895-0122-5334 | E270: SIM | F270: REGIDENT | G270: 1. Untuk selasa buka jam brp ya pak. Apa ada batasan kuota? 2. Trus maaf sebelumnya, apa masih untuk info mengenai BPJS apa masih bisa tanpa BPJS ya? 3. Baik, terima kasih. | H270: 1. Tidak ada batasan kuota, buka mulai pukul 08.00 - 12.00.
A271: 12 | B271: 45601 | C271: WHATSAPP | D271: +62 812-8611-2214 | E271: SAMSAT | F271: REGIDENT | G271: 1. Mohon info Pak/Bu, untuk Samsat keliling di Kantor UPTD itu yang mana ya? 2. Di kantor Pusvetma A.Yani atau yang mana ya? | H271: 1. Iya, di dalam kantor ya pak.
A272: 11 | B272: 45601 | C272: WHATSAPP | D272: '+62 822-4508-1616 | E272: SIM | F272: REGIDENT | G272: 1. Selamat pagi | H272: 1. pagi ada yg bisa dibantu?
... A299: 4 | B299: 45629 | C299: WHATSAPP | D299: +62 895-0453-4597 | E299: SIM | F299: REGIDENT | G299: 1. Selamat siang mau izin tanya untuk sekarang SIM keliling apa masih beroperasional ya terima kasih ? | H299: 1. masih pak/bu
A300: 5 | B300: 45629 | C300: WHATSAPP | D300: +62 896-2013-5630 | E300: SIM | F300: REGIDENT | G300: 1. Info sim corner sidoarjo 2. Knapa kamis pindah ke porong 3. Apa hari ini sim keliling buka | H300: 1. Untuk SIM keliling daerah Sidoarjo berada di sini pak/bu: - LIPPO PLAZA - PONDOK TJANDRA - RAMAYANA KRIAN Jam Pelayanan: - Senin - Kamis: 08.00 - 12.00 - Jumat & Sabtu: 08.00 - 11.00 2. Tidak ada pindah ke Porong pak 3. Buka bapak/ibu | K300: WHATSAPP | L300: =COUNTIF($C$297:$C$377,K300) -> 36 | N300: SAMSAT | O300: =COUNTIF($E$297:$E$377,N300) -> 4 | Q300: REGIDENT | R300: =COUNTIF($F$297:$F$377,Q300) -> 80
A301: 6 | B301: 45629 | C301: WHATSAPP | D301: +62 878-7628-5887 | E301: SIM | F301: REGIDENT | G301: Selamat siang. Izin bertanya, apa benar jika ingin perpanjang SIM A/C di SIM keliling Sidoarjo harus H-3 sebelum masa berlakunya habis? | H301: 1. Bisa dilakukan 2 minggu sebelum masa SIM habis pak/bu, hanya saja lebih diprioritaskan bila masa SIM sudah mendekati habis. | K301: FACEBOOK | L301: =COUNTIF($C$297:$C$377,K301) -> 3 | N301: SIM | O301: =COUNTIF($E$297:$E$377,N301) -> 76 | Q301: GAKKUM | R301: =COUNTIF($F$297:$F$377,Q301) -> 1
A302: 7 | B302: 45629 | C302: WHATSAPP | D302: +62 813-5320-1578 | E302: SIM | F302: REGIDENT | G302: 1. Selamat siang pak. Mau tanya untuk besok perpanjangan sim di lippo plaza apa ada pak? | H302: 1. ada pak/bu | K302: INSTAGRAM | L302: =COUNTIF($C$297:$C$377,K302) -> 42 | N302: LAKA | O302: =COUNTIF($E$297:$E$377,N302) -> 0 | Q302: PJR | R302: =COUNTIF($F$297:$F$377,Q302) -> 0
A303: 8 | B303: 45629 | C303: WHATSAPP | D303: +62 822-4519-2555 | E303: SIM | F303: REGIDENT | G303: 1. Halo mau tanya apakah bisa melakukan tes kesehatan dan psikologi di tempat sim keliling untuk perpanjangan sim di sidoarjo? | H303: 1. bisa pak/bu | K303: X/TWITTER | L303: =COUNTIF($C$297:$C$377,K303) -> 0 | N303: TILANG | O303: =COUNTIF($E$297:$E$377,N303) -> 1 | Q303: KAMSEL | R303: =COUNTIF($F$297:$F$377,Q303) -> 0
A304: 9 | B304: 45629 | C304: WHATSAPP | D304: +62 881-9089-695 | E304: SIM | F304: REGIDENT | G304: 1. Selamat pagi. Mau tanya, untuk sim keliling di lippo, buka jam berapa ya? | H304: 1. buka mulai pukul 08.00 - 12.00 | L304: =SUM(L300:L303) -> 81 | N304: LAIN-LAIN | O304: =COUNTIF($E$297:$E$377,N304) -> 0 | Q304: LAIN-LAIN | R304: =COUNTIF($F$297:$F$377,Q304) -> 0
A305: 10 | B305: 45629 | C305: WHATSAPP | D305: +62 822-3644-7474 | E305: SIM | F305: REGIDENT | G305: 1. Dimn diadakan pak? 2. Klu SIM keliling bisa bikin baru pak? | H305: 1. Persyaratan Perpanjangan SIM: KTP asli SIM asli Fotokopi KTP 2 lembar Fotokopi SIM 2 lembar Surat Keterangan Sehat 2. Tidak bisa pak/bu. 3. Hanya melayani perpanjangan SIM A dan C saja | O305: =SUM(L299:L303) -> 81
A306: 11 | B306: 45629 | C306: WHATSAPP | D306: +62 858-5997-2001 | E306: SIM | F306: REGIDENT | G306: 1. Selamat malam pak 2. Mau menanyakan soal perpanjangan SIM, untuk surat kesehatannya itu minta di institusi resmi dimana pak? 3. Terima kasih🙏 4. Terima kasih atas informasinya 5. Kalo di Lippo Plaza di sebelah mana pak/bu? | H306: 1. Bisa langsung datang ke lokasi ya pak/bu, sudah tersedia untuk cek kesehatan dan tes psikologi. 2. Di dalam mall ya pak.
A307: 12 | B307: 45630 | C307: WHATSAPP | D307: +62 811-5532-001 | E307: SIM | F307: REGIDENT | G307: 1. Assalamualaikum, selamat pagi Bapak/Ibu. Mohon maaf mau bertanya untuk mengurus NRKB Pilihan di Polda Jatim bisa menghubungi kemana ya Pak/Bu? Terima kasih 2. Baik.. terima kasih banyak atas infonya 🙏🏻 | H307: 1. Bisa menghubungi 085755983591 / 085730002090.
A308: 13 | B308: 45630 | C308: WHATSAPP | D308: +62 881-0821-08109 | E308: SIM | F308: REGIDENT | G308: Selamat pagi Mau tanya, surat keterangan sehat dari istitusi kesehatan resmi itu bisa di dapat dimana ? | H308: bisa langsung di dapat ditempat ya kak, sudah tersedia untuk cek kesehatan dan tes psikologi
A309: 14 | B309: 45630 | C309: WHATSAPP | D309: +62 812-3271-6070 | E309: SIM | F309: REGIDENT | G309: 1. Selamat pagi pak, mau menanyakan untuk SIM keliling ke Krian kapan ada jadwalnya lagi pak? Terima kasih infonya 🙏 2. Baik terimakasih pak | H309: 1. Untuk SIM keliling daerah Sidoarjo berada di sini pak/bu: - LIPPO PLAZA - PONDOK TJANDRA - RAMAYANA KRIAN 2. Jam Pelayanan: - Senin - Kamis: 08.00 - 12.00 - Jumat & Sabtu: 08.00 - 11.00 Persyaratan Perpanjangan SIM: - KTP asli - SIM asli - Fotokopi KTP 2 lembar - Fotokopi SIM 2 lembar - Surat Keterangan Sehat
A310: 15 | B310: 45630 | C310: WHATSAPP | D310: +62 812-1631-6022 | E310: SIM | F310: REGIDENT | G310: 1. Maaf apa benar ini nomor polsek Gubeng? 2. Maaf kalau mau tau no. tlp Polsek Gubeng cari tau di mana ya, soalnya saya coba googling no tlp yg tertera tdk bisa dihubungi. | H310: 1. Bukan, ini dari RTMC Polda Jatim. | P310: =MIN(R300:R304) -> 0
A311: 16 | B311: 45630 | C311: WHATSAPP | D311: +62 878-5208-7596 | E311: SIM | F311: REGIDENT | G311: 1. Malam min 2. Info perpanjang SIM A 3. Mintak bantuan min ini sudah mati tgl 7 kmarn apa bisa dibantu🙏🏻🙏🏻 4. Siapa tau BPK ibu admin bisa bantu 🤭 | H311: 1. Malam 2. Untuk SIM keliling daerah Sidoarjo berada di sini pak/bu: - LIPPO PLAZA - PONDOK TJANDRA - RAMAYANA KRIAN Jam Pelayanan: - Senin - Kamis: 08.00 - 12.00 - Jumat & Sabtu: 08.00 - 11.00 Persyaratan Perpanjangan SIM: - KTP asli - SIM asli - Fotokopi KTP 2 lembar - Fotokopi SIM 2 lembar - Surat Keterangan Sehat 3. Kalau sudah mati harus membuat SIM baru pak/bu.
A312: 37 | B312: 45633 | C312: INSTAGRAM | D312: Panjoel Jhuan Marvell | E312: SIM | F312: REGIDENT | G312: 1. Mohon Info.. SIM Keliling yang di GIANT Pondok Tjandra masih ada kah? | H312: 1. Masih ada pak/bu. Untuk SIM keliling daerah Sidoarjo berada di sini: - LIPPO PLAZA - PONDOK TJANDRA - RAMAYANA KRIAN Jam Pelayanan: - Senin sampai Kamis: 08.00 - 12.00 - Jumat dan Sabtu: 08.00 - 11.00
A313: 38 | B313: 45633 | C313: INSTAGRAM | D313: Rumah Baca Sahabat Hayva | E313: SIM | F313: REGIDENT | G313: Sore... Ijin bertanya. Utk KTP Surabaya apa bisa perpanjangan SIM di Sidoarjo ? Terima kasih... | H313: Untuk Sim keliling daerah sidoarjo berada di sini pak/bu 1. LIPPO PLAZA 2. PONDOK TJANDRA 3. RAMAYANA KRIAN Jam Pelayanan Mulai Pukul 08.00 - 12.00 Di hari Senin sampai hari Kamis bila hari jum at dan sabtu jam pelayanan dimulai pukul 08.00 - 11.00 Persyaratan Perpanjangan SIM: KTP asli SIM asli Fotokopi KTP 2 lembar Fotokopi SIM 2 lembar Surat Keterangan Sehat
A314: 39 | B314: 45633 | C314: INSTAGRAM | D314: Hapid Alviyan | E314: SIM | F314: REGIDENT | G314: Min ,saya perantau mau perpanjang sim C Mau tanya untuk kesehatannya di lippo sudah ada ya? | H314: sudah ada
A315: 40 | B315: 45633 | C315: INSTAGRAM | D315: Wahyu Zulfikar | E315: SIM | F315: REGIDENT | G315: Jarak maksimal perpanjangan sim c di sidoarjo itu berapa ya? maksimal H-3 atau harus H-1 sebelum sim nya mati. | H315: untuk perpanjangan bisa 2 minggu sebelum masa sim habis, hanya saja lebih di prioritaskan bila sim hampir habis
A316: 41 | B316: 45633 | C316: INSTAGRAM | D316: Diah Kusuma Wardani | E316: SIM | F316: REGIDENT | G316: sorry kak untuk pengurusan sim sidoarjo persyaratannya yg tertera yaa gimana untuk surat sehatnya? Diah Kusuma Wardani disediakan dari sananya atau ke dokter/puskesmas terdekat saja? | H316: untuk surat keterangan sehat bisa didapatkan ditempat ya kak, sudah tersedia untuk cek kesehatan den tes psikologi
A317: 42 | B317: 45633 | C317: INSTAGRAM | D317: Sobat Netizen Indonesia 🇮🇩 | E317: SIM | F317: REGIDENT | G317: Sore min, saya KTP Gresik dulu buat SIM di Polresta Sidoarjo. Apa bisa perpanjangan SIM C di SIM Keliling area Surabaya? | H317: bisa kak
A318: 43 | B318: 45633 | C318: INSTAGRAM | D318: Mada | E318: SIM | F318: REGIDENT | G318: Mau tnya untuk tanggal 5 apa ada di lippo sidoarjo? | H318: ada kak
A319: 44 | B319: 45633 | C319: INSTAGRAM | D319: ririssssm | E319: SIM | F319: REGIDENT | G319: Selamat Malam, mohon maaf mau tanya untuk surat keterangan sehat urus sendiri/disediakan disana? Terimakasih | H319: bisa langsung ditempat ya kak, sudah tersedia untuk cek kesehatan dan tes psikologi
A320: 45 | B320: 45633 | C320: INSTAGRAM | D320: Dhimas Aria Wirangga | E320: SIM | F320: REGIDENT | G320: Selamat siang. Izin bertanya, apa benar jika ingin perpanjang sim A/C di Sim keliling Sidoarjo harus H-3 sebelum masa berlakunya habis? | H320: untuk sim bisa diperpanjang h-2 minggu pak/bu hanya saja lebih di prioritaskan untuk sim A/C yang masa simnya hampir habis
A321: 46 | B321: 45633 | C321: INSTAGRAM | D321: Wiwik Nopendaria | E321: SIM | F321: REGIDENT | G321: Sore admin... mohon ijin bertanya saya sim nya terlambat 8 hari... apa bisa perpanjangan sim admin? | H321: mohon maaf tidak bisa ya kak, bila sim terlambat diperpanjang diharuskan untuk membuat sim baru
A322: 47 | B322: 45633 | C322: INSTAGRAM | D322: Nanang Krisna | E322: SIM | F322: REGIDENT | G322: Maksimal batas perpanjangan simnya berapa hari kak? Nanang Krisna H-7 hari sebelum habis bisa kah kak buat perpanjangan SIM? | H322: bisa kak
... A385: 12 | B385: 45663 | C385: WHATSAPP | D385: +62 823-3536-0133: | E385: LAIN-LAIN | F385: LAIN-LAIN | G385: 1. Selamat siang kak mau tanya ? Utk pembuatan SKCK di Polda jatim bagi KTP luar daerah, bisa kak? 2. KTp sy kepulauan Masalembu, sy bekerja di Lab. Perikanan SBY. 3. Utk pemberkasan PPPK disyaratkan utk membuat SKCK.🙏 4. Mohon petunjuk kak?🙏 | H385: Siang mhn maaf kami tanyakan terlebih dahulu
A386: 18 | B386: 45663 | C386: FACEBOOK | D386: Sugih Seger Waras | E386: SAMSAT | F386: REGIDENT | G386: Pak...tanya... rincian pajak 5 thunan apa aja ya... (ganti Plat nomor).. makasih biayanya... Sugih Seger Waras Motor honda beat 2015 Ok Pak Matur nuwun 🙏🙏🙏 2. Pak Bos tanya... Klo Plat W Gresik...ganti Plat 5 thnn di Sby..Apa bisa Pak .. Klo bisa...Mau ngurus di Samsat Manyar aja...biar gag Jauh2 ke Gresik Sugih Seger Waras Makasih... Saya tunggu jawabannya ya Pak... 🙏🙏🙏 Siap... Terima Kasih Pak... 🙏🙏🙏 | H386: Info Layanan Bapenda Jatim biaya PNBP stnk : Rp. 100.000 plat nomor : 60.000 untuk biaya pajak bisa cek di : https://info.dipendajatim.go.id/index.php?page=info_pkb terima kasih kembali tidak bisa pak, bila perpanjang 5 tahunan harus menuju ke samsat asal | N386: =SUM(M369:M373) -> 0
A387: 13 | B387: 45664 | C387: WHATSAPP | D387: +62 857-3031-8548 | E387: SIM | F387: REGIDENT | G387: Selamat siang Mohon informasi untuk pelayanan perpanjang SIM, jam operasional nya jam berapa? Sya warga kec. dawarblandong | H387: Kota mana ya pak/bu | J387: WHATSAPP | K387: =COUNTIF($C$375:$C$427,J387) -> 29 | M387: SAMSAT | N387: =COUNTIF($E$297:$E$377,M387) -> 4 | P387: REGIDENT | Q387: =COUNTIF($F$297:$F$377,P387) -> 80
A388: 14 | B388: 45665 | C388: WHATSAPP | D388: +62 823-3052-0056 | E388: SIM | F388: REGIDENT | G388: 1. Selamat malem kak 2. Mw tanyak unk perpanjang SIM di Lippo apa hrs ambil nomor antrian dlu ya? 3. SIM saya terakhir tgl 8 Januari 4. Berarti besok bisa ya | H388: 1. Bisa langsung antri di tempat ya pak/bu 2. Bisa pak/bu | J388: FACEBOOK | K388: =COUNTIF($C$375:$C$427,J388) -> 7 | M388: SIM | N388: =COUNTIF($E$297:$E$377,M388) -> 76 | P388: GAKKUM | Q388: =COUNTIF($F$297:$F$377,P388) -> 1
A389: 15 | B389: 45666 | C389: WHATSAPP | D389: +62 852-5363-3875 | E389: SIM | F389: REGIDENT | G389: 1. Ndan mau tanya apakah bisa perpanjang SIM di SIM keliling sedangkan saya masih dalam proses SIM online presentasi masih 40% padahal sudah 9 jari prosesnya 2. Tapi masa berlaku SIM saya tgl 19 sedangkan sekarang tgl 9 kurang 10 hari masa berlaku SIM saya | H389: 1. Bila sudah melakukan registrasi sim online lebih baik menunggu untuk prosesnya hingga selesai pak/bu | J389: INSTAGRAM | K389: =COUNTIF($C$375:$C$427,J389) -> 17 | M389: LAKA | N389: =COUNTIF($E$297:$E$377,M389) -> 0 | P389: PJR | Q389: =COUNTIF($F$297:$F$377,P389) -> 0
A390: 16 | B390: 45666 | C390: WHATSAPP | D390: +62 822-3014-3335 | E390: SIM | F390: REGIDENT | G390: 1. Selamat Siang Bapak mau menanyakan informasi perpanjangan SIM C, utk di Ramayana Krian apa buka setiap hari? 2. Terima kasih banyak Pak/Ibu atas informasinya 🙏🏻🙏🏻 | H390: 1. Untuk Sim keliling daerah sidoarjo berada di sini pak/bu - LIPPO PLAZA - PONDOK TJANDRA - RAMAYANA KRIAN Jam Pelayanan Mulai Pukul 08.00 - 12.00 Di hari Senin sampai hari Kamis bila hari Jumat dan Sabtu jam pelayanan dimulai pukul 08.00 - 11.00 | J390: X/TWITTER | K390: =COUNTIF($C$375:$C$427,J390) -> 0 | M390: TILANG | N390: =COUNTIF($E$297:$E$377,M390) -> 1 | P390: KAMSEL | Q390: =COUNTIF($F$297:$F$377,P390) -> 0
A391: 17 | B391: 45666 | C391: WHATSAPP | D391: +62 882-0091-38169 | E391: SIM | F391: REGIDENT | G391: 1. Selamat Siang, Pak. Maaf mau tanya? SIM KELILING di Ramayana Krian, Selain tanggal 8 Januari. Tanggal brp saja ya, yg standby di Ramayana Krian? 2. Apakah minggu depan juga ada? 3. Dan setiap hari apa, Standby di Ramayana Krian?? 4. Terima kasih 🙏🙏 | H391: 1. Untuk Sim keliling daerah Sidoarjo berada di sini pak/bu - LIPPO PLAZA - PONDOK TJANDRA - RAMAYANA KRIAN Jam Pelayanan Mulai Pukul 08.00 - 12.00 Di hari Senin sampai hari Kamis, bila hari Jumat dan Sabtu jam pelayanan dimulai pukul 08.00 - 11.00 | K391: =SUM(K387:K390) -> 53 | M391: LAIN-LAIN | N391: =COUNTIF($E$297:$E$377,M391) -> 0 | P391: LAIN-LAIN | Q391: =COUNTIF($F$297:$F$377,P391) -> 0
A392: 19 | B392: 45666 | C392: FACEBOOK | D392: Daniel Yudha Kumoro | E392: LAIN-LAIN | F392: KAMSEL | G392: Bismillah. Mohon ijin. Traffic light Gebang Lingkar Timur Sidoarjo yang ke arah utara atau dari selatan mati. Lalu depan informa jalannya rusak. | H392: Terimakasih informasinya Bisa menuju ke Polsek terdekat pak/bu
A393: 20 | B393: 45666 | C393: FACEBOOK | D393: Naufal Aris | E393: SIM | F393: REGIDENT | G393: Halo apakah besok sim kelilinh ada ya pak? Sudah Pak, SIM saya sudah slesai scara online, tdak jd bkin di sim,kelilinh, trimakssih | H393: Untuk Sim keliling daerah sidoarjo berada di sini pak/bu 1. LIPPO PLAZA 2. PONDOK TJANDRA 3. RAMAYANA KRIAN Jam Pelayanan Mulai Pukul 08.00 - 12.00 Di hari Senin sampai hari Kamis bila hari jum at dan sabtu jam pelayanan dimulai pukul 08.00 - 11.00
A394: 21 | B394: 45669 | C394: FACEBOOK | D394: Cak Adi | E394: SIM | F394: REGIDENT | G394: ndan tgl 05 apakah ada SIM keliling di pondok candra Berarti hari senin sampai jumat ada SIM klilingya Persyaratan apa saja yang dibawa untuk perpanjang SIM nya Matur nuwon infonya | H394: tanggal 5 hari minggu pelayanan tutup pak Untuk Sim keliling daerah sidoarjo berada di sini pak/bu 1. LIPPO PLAZA 2. PONDOK TJANDRA 3. RAMAYANA KRIAN Jam Pelayanan Mulai Pukul 08.00 - 12.00 Di hari Senin sampai hari Kamis bila hari jum at dan sabtu jam pelayanan dimulai pukul 08.00 - 11.00 ktp asli, sim lama, fotokopi sim dan ktp 2 kali
A395: 22 | B395: 45671 | C395: FACEBOOK | D395: Raden Mustopo | E395: SIM | F395: REGIDENT | G395: Maaf.. Untuk jadwal sim kelililing di Ramayana krian, hari jumat (17 Januari 2025 ) dan sabtu ( 18 Januari 2025 ) .. Terimakasih | H395: Untuk Sim keliling daerah sidoarjo berada di sini pak/bu 1. LIPPO PLAZA 2. PONDOK TJANDRA 3. RAMAYANA KRIAN Jam Pelayanan Mulai Pukul 08.00 - 12.00 Di hari Senin sampai hari Kamis bila hari jum at dan sabtu jam pelayanan dimulai pukul 08.00 - 11.00
A396: 23 | B396: 45671 | C396: FACEBOOK | D396: Dimas Narendra | E396: SAMSAT | F396: REGIDENT | G396: Siang kak Dimas Narendra Kak mohon info dong berkas untuk buka blokir BPKB untuk mutasi kendaraan R4 | H396: mohon waktu
A397: 24 | B397: 45672 | C397: INSTAGRAM | D397: Lailatul Mafula | E397: SIM | F397: REGIDENT | G397: Selamat siang Pak/Bu. Mau bertanya, paman saya tgl 28 des perpanjangan sim C. Tp sampai sekarang blm selesai. Dan masih 40%. Kemungkinan kenapa ya pak bu? Iya kak, tp tgl 17 Januari expired simnya. Gimana kalau sampai tgl 17 belum jadi kak? Mohon bantuannya kak? M1553241228079ON A.n Ponidi Mohon segera diproses kak, expired 17 Januari 🥲 Mohon dong kak, segera diproses 🙏 | H397: masih proses kak, dan antrian proses sesuai dengan kapan di daftarkan di aplikasinya jadi mohon ditunggu saja mohon maaf kak untuk antrian dari sim online sesuai urutan jadi kami tidak bisa membantu untuk memproses, dan tugas kami disini hanya untuk memberikan informasi dan untuk sim yang terlewat/expired lebih dulu sebelum sim online selesai tidak masalah kak karena sudah di ajukan untuk perpanjangan sim online sebelum sim expired
...

Sheet Sheet3
B1: [09:36, 01/06/2025 | C1: +62 856-3230-700 | D1: Selamat pagi
B2: [09:37, 01/06/2025 | C2: +62 856-3230-700 | D2: Untuk perpanjang SIM A di Kahuripan nirwana,ada syarat kesehatan dokter SM psikologi,itu bisa dilakukan disana atau mencari sendiri sebelum perpanjangan ya?
B3: [19:44, 01/06/2025 | C3: RTMC JATIM | D3: selamat malam kak maaf tadi ada trobel sistem jadi lama balas nya
B4: [19:44, 01/06/2025 | C4: RTMC JATIM | D4: untuk kesehatan sm psikologi ada di tempat kak
B5: [20:13, 01/06/2025 | C5: +62 856-3230-700 | D5: Jadi yg perlu disiapkan dr rumah apa aja kak?
B6: [20:14, 01/06/2025 | C6: RTMC JATIM | D6: itu kak syarat nya sim yg akan perpanjang dan ktp
B7: [20:14, 01/06/2025 | C7: +62 856-3230-700 | D7: Oh ya untuk SIM habis tgl 11 kak,besok sudah bisa perpanjang kan ya?
B8: [20:14, 01/06/2025 | C8: RTMC JATIM | D8: sudah bisa kak
B9: [20:15, 01/06/2025 | C9: +62 856-3230-700 | D9: Kak yg di Kahuripan nirwana g ada ya?
B10: [20:15, 01/06/2025 | C10: +62 856-3230-700 | D10: Diganti di Lippo?
B11: [20:16, 01/06/2025 | C11: RTMC JATIM | D11: ada kak
B12: [20:17, 01/06/2025 | C12: RTMC JATIM | D12: lippo dari polda kalau di kahuripan dari polresta sidoarjo
... B23: [20:22, 01/06/2025 | C23: RTMC JATIM | D23: tidak harus kak
B24: [20:22, 01/06/2025 | C24: RTMC JATIM | D24: kalau awal bulan seperti ini kebanyakan rame kak | L24: +62 811-3070-2826
B25: [20:23, 01/06/2025 | C25: RTMC JATIM | D25: bawah foto copy ktp sm sim nya masing² 3 lembar kak biar tidak bingung cari foto copy lg | L25: +62 822-6558-9819
B26: [20:26, 01/06/2025 | C26: +62 856-3230-700 | D26: Bisa diinfo lokasi yg di pocan? | L26: +62 822-5765-2986
B27: [20:45, 01/06/2025 | C27: RTMC JATIM | D27: ruko palm kak | L27: +62 878-5808-6000
B28: belakang giant yg sudah tutup | L28: +62 895-1590-0725
B29: [20:47, 01/06/2025 | C29: +62 856-3230-700 | D29: Makasih kak infonya ❤️ | L29: +62 822-3421-0313
B30: [20:48, 01/06/2025 | C30: RTMC JATIM | D30: sama sama kak | L30: +62 897-9799-904
B31: [20:48, 01/06/2025 | C31: RTMC JATIM | D31: besok sendiri apa sm suami? | L31: +62 878-5392-1505
B32: [20:48, 01/06/2025 | C32: RTMC JATIM | D32: saran saya di temani suami kak takut nya anak nya rewel pas saat tes psiko atau kesehatan | L32: +62 822-3481-9676
B33: [20:49, 01/06/2025 | C33: RTMC JATIM | D33: atau bawa saudara | L33: +62 823-3554-1927
B34: [20:49, 01/06/2025 | C34: +62 856-3230-700 | D34: Sama 2 lansia dan 2 bayi 5 bulan 🤭 | L34: +62 813-3612-5956
B35: [20:49, 01/06/2025 | C35: +62 856-3230-700 | D35: Siap kak
B36: [20:49, 01/06/2025 | C36: RTMC JATIM | D36: oh ya kak alhamdulillah kalau ada kakek nenek nya
B37: [20:50, 01/06/2025 | C37: +62 856-3230-700 | D37: Iya kak,semoga g antri banyak besok
B38: [20:50, 01/06/2025 | C38: +62 856-3230-700 | D38: Makasih kak,met istirahat ❤️
B39: [20:51, 01/06/2025 | C39: RTMC JATIM | D39: yaa semoga kak
B40: kadang juga kasian kalau bawa bayi itu 🥹
B41: [20:51, 01/06/2025 | C41: RTMC JATIM | D41: terimakasih kak 🥰

Sheet Copy of REKAP
A1: NO | B1: PERTANYAAN | C1: JAWABAN
A2: 1 | B2: - Selamat pagi Bapak/Ibu, saya Rizki dari Surabaya, mohon izin bertanya/info, untuk pengurusan kartu induk BPKB yang hilang perlu waktu berapa lama ya? Atau adakah nomor/media/kanal yang bisa dihubungi untuk bertanya karena saya cari melalui internet/medsos sepertinya belum ada? Mohon bantuannya bapak/ibu. Terimakasih🙏🏻🙏🏻 | C2: - bisa dibantu nopolnya? kami bantu cek
A3: 2 | B3: - Assalamualaikum pak selamat siang- Saya mau ngambil stnk tanpa harus di sidang gimana caranya?- Ini tandanya polsek gubeng,Tapi malah di suruh sidang di Sukomanunggal.- Katanya bapak nya saya di suruh (ngurus atau disidang)Nah saya pilih di urus pak biar cepat dan clear. | C3: - walaikumsalam selamat siang- ada yg bisa kami bantu- Wilayah mana pak/bu- ada no tilangnya kita bantu cek terlebih dahulu- silahkan datang di satpas colombo untuk meminta kode briva di kantor tilang polrestabes surabaya
A4: 3 | B4: -Selamat pagi-Perkenalkan saya Herlambang,-Mohon bantuan petunjuknya Bapak/Ibu, untuk persyaratan penerbitan Surat Rekomendasi Polda Jatim, untuk keperluan pendaftaran STNK & BPKB kendaraan di kantor Samsat daerah Jawa Timur.-Domisili Banyuwangi Pak-Namun saat ini kendaraan berada di Bekasi, Jawa Barat Pak/Bu-Baik terimakasih atas informasinya, Izin bertanya apakah persyaratan penerbitan Surat Rekomendasi bisa disampaikan melalui jasa pengiriman dokumen (Pos) atau melalui email Pak/Bu?--Karena saat ini saya tinggal di bekasi namun data KTP masih beralamat di Banyuwangi. Terimakasih🙏-Baik Bapak/Ibu terimakasih atas informasinya🙏-Sehubungan dengan persyaratan yang dimohonkan untuk penerbitan surat Rekomendasi Polda Jatim, ada persamaan berkas yang disampaikan untuk penerbitan BPKB dari kantor Samsat Banyuwangi sesuai persyaratan terlampir Pak/Bu-Mohon izin bertanya kembali Pak/bu apakah ketika pengajuan permohonan penerbitan surat rekomendasi Polda Jatim Dokumen Asli hanya untuk ditunjukkan dan yang disampaikan untuk surat rekomendasi adalah dokumen duplikat/copy Bapak/Ibu? | C4: -pemenang lelang domisili mana pak/bu-atau bisa difotokan dokumen lelalng nya-mohon maaf tidak bisa, dikarenakan butuh berkas asli, dan apabila dikirim melalui POS dikhawatirkan tidak terkirim, trims-Untuk surat yg dibawa ke polda harus asli pak/bu
A5: 5 | B5: Untuk Sidoarjo dimana aja untuk bayar pajak spdh | C5: silahkan datang di samsat corner lotte mart,samsat keliling kota,samsat keliling krian,samsat payment point wadung asri,samsat payment point samsat lama,samsat payment point bank jatim taman, samsat payment point puspa agro terima kasih
A6: 6 | B6: 1. Bayar pajak kendaraan tanpa ktp pemilik pertama apakah bisa???2.Siap 🙏🙏🙏 | C6: mohon maaf tidak bisa, apabila sudah berpindah tangan bisa balik nama di samsat asal, terima kasih
A7: 4 | B7: -Selamat siang, betul dengan akun whatsapp polsek tegalsari surabaya?-Mohon maaf, adakah kontak whatsapp polsek tegalsari yang bisa saya hubungi Pak/Bu?-Saya ingin menanyakan perihal kerabat saya yg terakhir kali infonya sedang berada di polsek tegalsari Surabaya🙏🏻--Baik, terimakasih bantuannya Pak/Bu 🙏🏻-Baik, untuk nomor whatsapp nya belum ada ya Pak/Bu? | C7: -dengan rtmc polda jatim-Ada yg bisa dibantu-Mhn waktu-izin pak/bu ini untuk nomor dari polsek tegal sari 031 5341052-untuk sementara nomor dari polsek tegalsari hanya ini saja
A8: 7 | B8: Maaf, bs untuk upgrade SIM A ke B1 | C8: mohon maaf tidak bisa sim keliling hanya melayani perpanjangan sim A dan C saja, terima kasih
A9: 8 | B9: 1. Kalau perpanjang SIM maksimal berapa hari sebelum masa berlaku2. ini berlaku seluruh Jawa timur | C9: 1. sebelum masa berlaku habis2. iya pak
A10: 1 | B10: 1. SIM saya surabaya, sekarang KTP Sidoarjo. Mau memperpanjang SIM. Mohon pencerahan dari ditlantas Polda.Terima kasih.2.Terima kasih pencerahannya. | C10: 1. kalau SIM A dan C bisa diperpanjang dimana saja mas, asal SIM tersebut belum kadaluarsa dan mengikuti KTP alamat baru
A11: 2 | B11: 1. Apakah di sim keliling di sediakan tempat psikologi dan surat kesehatan | C11: 1. sudah tersedia
A12: 3 | B12: 1. mutasi masuk apakah bisa langsung ke samsat tujuan?2. mobil plat N Malang masuk ke Surabaya samsat Kedung Cowek dan mobil plat Bandar Lampung masuk ke Surabaya samsat Kedung Cowek ndan, mohon pencerahannya, terima kasih3.sudah tidak perlu cabut berkas lagi di samsat asal ya ndan?4. siap, terima kasih infonya ndan 🙏🙏🙏 | C12: 1.dari samsat mana kemana pak2. apabila dari plat N langsung ke samsat tujuan namun untuk plat luar wilayah jawa timur ke polda terlebih dahulu, trims3. tetap cabut di samsat asal pak
A13: 4 | B13: 1. Perpanjang SIM a/c bulan 10 matinya , dan diperpanjang bulan 6 sekarang apa bisa2. siap terima kasih | C13: 1. bisa pak, dan masa berlaku mengikuti tgl pendaftaran perpanjangan SIM2. terima kasih kembali
... A196: 59 | B196: 1. Siang admin rtmc jatim2. Untuk SIM yg sudah kadaluwarsa 13 hari apakah masih bisa perpanjangan?3. Karena saya pikir kedaluwarsa sesuai tanggal lahir, ternyata tanggal pembaruan terakhir4. Terimakasih Informasinya | C196: 1. tidak bisa pak/bu bila masa sim berlaku habis maka diharuskan membuat sim baru
A197: 66
A198: 67
A199: 68
A200: 1 | B200: 1. Selamat pagi2. Info jadwal SIM di Surabaya | C200: 1. untuk sim keliling surabaya belum ada jadwalnya pak/bu sementara hanya di sidoarjo saja
A201: 2 | B201: 1.Selamat siang pak Saya mau nanya Sim nganjuk apa bisa di perpanjang di sidoarjo ?2. Persyaratannya apa saja pak?3. Siap pak besok berangkat ke lippo | C201: 1. bisa pak/bu asalkan sudah e-ktp2. 📝 Persyaratan Perpanjangan SIM:- KTP asli- SIM asli- Fotokopi KTP 2 lembar- Fotokopi SIM 2 lembar- Surat Keterangan Sehat⚠️ Catatan Penting:- Layanan hanya untuk perpanjangan SIM A dan C.- Tidak melayani penerbitan SIM baru.
A202: 3 | B202: 1. Selamat siang. Mohon informasinya pelayanan tutup jam berapa2. Kami dari kota Mojokerto mau urus berkas mutasi kendaraan kami3. Siap terima kasih 🙏🙏4. Mohon ijin Bapak menayangkan apakah hari Sabtu buka untuk pelayanan.petunjuk Terimakasih 🙏🙏 | C202: 1. RTMC JATIM: jam 12.00 pak/bu2. buka pak/bu pelayanan sampai jam 11.00
A203: 4 | B203: 1. Selamat malam2. SiapTerima kasih infonya 🙏🙏🙏 | C203: 1. Mohon ijin komandan untuk jadwal SIM keliling per tanggal 2 Oktober 2024 di laksanakan di mana ya ??🙏🙏🙏 1. Untuk Sim keliling daerah sidoarjo berada di sini pak/bu 1. LIPPO PLAZA 2. PONDOK TJANDRA 3. RAMAYANA KRIAN Jam Pelayanan Mulai Pukul 08.00 - 12.00 Di hari Senin sampai hari Kamis bila hari jum at dan sabtu jam pelayanan dimulai pukul 08.00 - 11.00
A204: 5 | B204: 1. Halo min2. Minta info jadwal sim keliling di Ramayana Krian. Hari apa ya3. Untuk biaya perpanjang SIM C berapa ya?4. Terimakasih | C204: 1. Untuk SIM keliling daerah Sidoarjo berada di sini, Pak/Bu:LIPPO PLAZAPONDOK TJANDRARAMAYANA KRIANJam pelayanan mulai pukul 08.00 - 12.00 di hari Senin sampai hari Kamis. Bila hari Jumat dan Sabtu, jam pelayanan dimulai pukul 08.00 - 11.002. Untuk PNBP SIM A perpanjangan: 80.000Untuk PNBP SIM C perpanjangan: 75.000
A205: 6 | B205: 1. Selamat sore mohon maaf mengganggu saya Pak Zaenudin mohon info jadwal utk SIM keliling tanggal 04 Oktober 2024🙏 2. Wilayah Sidoarjo🙏 3. Ok siap Bapak/Ibu terimakasih untuk informasinya 🙏🙏 4. Selamat malam🫡 | C205: 1. Untuk SIM keliling daerah Sidoarjo berada di sini, Pak/Bu: - LIPPO PLAZA - PONDOK TJANDRA - RAMAYANA KRIAN Jam pelayanan mulai pukul 08.00 - 12.00 di hari Senin sampai hari Kamis. Bila hari Jumat dan Sabtu, jam pelayanan dimulai pukul 08.00 - 11.00
A206: 7 | B206: 1. Mohon maaf untuk SIM kelilingnya untuk hari Minggu di daerah Sidoarjo apakah ada 2. Untuk surat kesehatannya dibuat sekalian di SIM keliling bisa apa enggak ya 3. Dan bila bisa, biayanya berapa 4. Biayanya berapa ya 5. Biaya kesehatan sama psikologinya di situ bayar berapa ya 6. Itu tes kesehatan aja atau sudah sama psikologi 7. Oh.. Ok.. Terimakasih atas informasinya | C206: 1. Untuk hari Minggu, pelayanan libur ya, Pak/Bu 2. Bisa, Pak/Bu 3. Untuk PNBP SIM A perpanjangan: 80.000 Untuk PNBP SIM C perpanjangan: 75.000 CATATAN: Biaya kesehatan dan psikologi di luar PNBP Polri 4. Mohon maaf, Pak/Bu. Dikarenakan kesehatan sama psikologi di luar wewenang kami, jadi kami tidak bisa memutuskan untuk biaya tes kesehatan dan psikologi 5. Tetapi biasanya untuk harga include rentang harga 250 - 300 ribu, Pak/Bu 6. Sudah semua include kesehatan, psikologi, dan biaya perpanjang SIM 7. Terimakasih kembali
A207: 8 | B207: 1. Pak mau tanya 2. Kalau SIM Probolinggo diperpanjang di Sidoarjo apakah bisa atau tidak ya? 🙏🏼🙏🏼🙏🏼 | C207: 1. Bisa, Pak/Bu, asalkan sudah e-KTP
A208: 9 | B208: 1. Assalamualaikum kak, perpanjangan SIM C kena biaya berapa ya | C208: 1. Untuk PNBP SIM A perpanjangan: 80.000 Untuk PNBP SIM C perpanjangan: 75.000 CATATAN: Biaya kesehatan dan psikologi di luar PNBP Polri
A209: 10 | B209: 1. Selamat sore 🙏 Mohon ijin bertanya Untuk sistem antrian seperti apa ya? Dan untuk surat sehat apakah boleh dari klinik mana saja? 2. Terima kasih 🙏 3. Baik, terima kasih banyak informasinya 🙏 | C209: 1. Untuk sistem antrian langsung, Pak/Bu. Untuk surat kesehatan bisa dari luar, Pak/Bu
A210: 11 | B210: 1. Mau tanya untuk SIM keliling daerah Pondok Candra mana nya ya? | C210: 1. Di depan Bank BCA Pocan ya, Pak/Bu
A211: 12 | B211: 1. Siang pak/bu 2. Mau tanya perpanjangan SIM C Sidoarjo, surat keterangan sehatnya ngurusnya di mana? 3. Oh ok trims 4. Siang pak/bu mau tanya SIM C mau habis kurang 2 minggu lagi, apakah bisa diurus? | C211: 1. Di tempat perpanjangan SIM cek kesehatan sudah tersedia, Pak/Bu 2. Bisa, Pak/Bu
... A303: 4 | B303: 1. Selamat siang mau izin tanya untuk sekarang SIM keliling apa masih beroperasional ya terima kasih ? | C303: 1. masih pak/bu
A304: 5 | B304: 1. Info sim corner sidoarjo 2. Knapa kamis pindah ke porong 3. Apa hari ini sim keliling buka | C304: 1. Untuk SIM keliling daerah Sidoarjo berada di sini pak/bu: - LIPPO PLAZA - PONDOK TJANDRA - RAMAYANA KRIAN Jam Pelayanan: - Senin - Kamis: 08.00 - 12.00 - Jumat & Sabtu: 08.00 - 11.00 2. Tidak ada pindah ke Porong pak 3. Buka bapak/ibu | F304: WHATSAPP | G304: =COUNTIF(#REF!,F304) -> 0 | I304: SAMSAT | J304: =COUNTIF(#REF!,I304) -> 0 | L304: REGIDENT | M304: =COUNTIF(#REF!,L304) -> 0
A305: 6 | B305: Selamat siang. Izin bertanya, apa benar jika ingin perpanjang SIM A/C di SIM keliling Sidoarjo harus H-3 sebelum masa berlakunya habis? | C305: 1. Bisa dilakukan 2 minggu sebelum masa SIM habis pak/bu, hanya saja lebih diprioritaskan bila masa SIM sudah mendekati habis. | F305: FACEBOOK | G305: =COUNTIF(#REF!,F305) -> 0 | I305: SIM | J305: =COUNTIF(#REF!,I305) -> 0 | L305: GAKKUM | M305: =COUNTIF(#REF!,L305) -> 0
A306: 7 | B306: 1. Selamat siang pak.Mau tanya untuk besok perpanjangan sim di lippo plaza apa ada pak? | C306: 1. ada pak/bu | F306: INSTAGRAM | G306: =COUNTIF(#REF!,F306) -> 0 | I306: LAKA | J306: =COUNTIF(#REF!,I306) -> 0 | L306: PJR | M306: =COUNTIF(#REF!,L306) -> 0
A307: 8 | B307: 1. Halo mau tanya apakah bisa melakukan tes kesehatan dan psikologi di tempat sim keliling untuk perpanjangan sim di sidoarjo? | C307: 1. bisa pak/bu | F307: X/TWITTER | G307: =COUNTIF(#REF!,F307) -> 0 | I307: TILANG | J307: =COUNTIF(#REF!,I307) -> 0 | L307: KAMSEL | M307: =COUNTIF(#REF!,L307) -> 0
A308: 9 | B308: 1. Selamat pagi. Mau tanya, untuk sim keliling di lippo, buka jam berapa ya? | C308: 1. buka mulai pukul 08.00 - 12.00 | G308: =SUM(G304:G307) -> 0 | I308: LAIN-LAIN | J308: =COUNTIF(#REF!,I308) -> 0 | L308: LAIN-LAIN | M308: =COUNTIF(#REF!,L308) -> 0
A309: 10 | B309: 1. Dimn diadakan pak?2. Klu SIM keliling bisa bikin baru pak? | C309: 1. Persyaratan Perpanjangan SIM:KTP asliSIM asliFotokopi KTP 2 lembarFotokopi SIM 2 lembarSurat Keterangan Sehat2. Tidak bisa pak/bu.3. Hanya melayani perpanjangan SIM A dan C saja | J309: =SUM(G303:G307) -> 0
A310: 11 | B310: 1. Selamat malam pak 2. Mau menanyakan soal perpanjangan SIM, untuk surat kesehatannya itu minta di institusi resmi dimana pak? 3. Terima kasih🙏 4. Terima kasih atas informasinya 5. Kalo di Lippo Plaza di sebelah mana pak/bu? | C310: 1. Bisa langsung datang ke lokasi ya pak/bu, sudah tersedia untuk cek kesehatan dan tes psikologi. 2. Di dalam mall ya pak.
A311: 12 | B311: 1. Assalamualaikum, selamat pagi Bapak/Ibu. Mohon maaf mau bertanya untuk mengurus NRKB Pilihan di Polda Jatim bisa menghubungi kemana ya Pak/Bu? Terima kasih 2. Baik.. terima kasih banyak atas infonya 🙏🏻 | C311: 1. Bisa menghubungi 085755983591 / 085730002090.
A312: 13 | B312: Selamat pagi Mau tanya, surat keterangan sehat dari istitusi kesehatan resmi itu bisa di dapat dimana ? | C312: bisa langsung di dapat ditempat ya kak, sudah tersedia untuk cek kesehatan dan tes psikologi
A313: 14 | B313: 1. Selamat pagi pak, mau menanyakan untuk SIM keliling ke Krian kapan ada jadwalnya lagi pak? Terima kasih infonya 🙏2. Baik terimakasih pak | C313: 1. Untuk SIM keliling daerah Sidoarjo berada di sini pak/bu: - LIPPO PLAZA - PONDOK TJANDRA - RAMAYANA KRIAN 2. Jam Pelayanan: - Senin - Kamis: 08.00 - 12.00 - Jumat & Sabtu: 08.00 - 11.00 Persyaratan Perpanjangan SIM: - KTP asli - SIM asli - Fotokopi KTP 2 lembar - Fotokopi SIM 2 lembar - Surat Keterangan Sehat
A314: 15 | B314: 1. Maaf apa benar ini nomor polsek Gubeng? 2. Maaf kalau mau tau no. tlp Polsek Gubeng cari tau di mana ya, soalnya saya coba googling no tlp yg tertera tdk bisa dihubungi. | C314: 1. Bukan, ini dari RTMC Polda Jatim. | K314: =MIN(M304:M308) -> 0
A315: 16 | B315: 1. Malam min 2. Info perpanjang SIM A 3. Mintak bantuan min ini sudah mati tgl 7 kmarn apa bisa dibantu🙏🏻🙏🏻 4. Siapa tau BPK ibu admin bisa bantu 🤭 | C315: 1. Malam 2. Untuk SIM keliling daerah Sidoarjo berada di sini pak/bu: - LIPPO PLAZA - PONDOK TJANDRA - RAMAYANA KRIAN Jam Pelayanan: - Senin - Kamis: 08.00 - 12.00 - Jumat & Sabtu: 08.00 - 11.00 Persyaratan Perpanjangan SIM: - KTP asli - SIM asli - Fotokopi KTP 2 lembar - Fotokopi SIM 2 lembar - Surat Keterangan Sehat 3. Kalau sudah mati harus membuat SIM baru pak/bu.
A316: 17 | B316: 1. Pak jadwal sim keliling depan ramayana krian tanggal 6 desember ada apa tidak pak | C316: 1. ada pak kemarin bisa dilihat dimedsos kami
A317: 18 | B317: Untuk sim keliling daerah sidoarjo jawatimur. Surat keterangan sehat dapat nya dari mana ya? Dan biaya perpanjangan sim C berapa? | C317: untuk PNBP SIM A Panjang : 80.000untuk PNBP SIM C Panjang : 75.000CATATAN : Biaya Kesehatan dan Psikologi diluar PNBP polri
A318: 19 | B318: 1. Assalamualaikum... Maaf...minta tolong info jadwal perpanjangan SIM hari Kamis, 12 Desember...terima kasih 🙏🏻 2. Nggih...terimakasih infonya 🙏🏻 | C318: 1. Untuk SIM keliling daerah Sidoarjo berada di sini pak/bu: - LIPPO PLAZA - PONDOK TJANDRA - RAMAYANA KRIAN Jam Pelayanan: - Senin - Kamis: 08.00 - 12.00 - Jumat & Sabtu: 08.00 - 11.00
A319: 20 | B319: Selamat malam, Mohon maaf mau tanya. Persyaratan buat perpanjangan sim keliling apa saja? 🙏🏼 | C319: Persyaratan Perpanjangan SIM:KTP asliSIM asliFotokopi KTP 2 lembarFotokopi SIM 2 lembarSurat Keterangan Sehat
A320: 21 | B320: 1. Mau tanya mengenai perpanjangan SIM, untuk surat sehat bisa dari dokter umum? 2. Kalau nama di SIM ada yg salah itu tetep bisa langsung perpanjangan kah? | C320: 1. Tidak apa-apa selama dokter tersebut sudah mendapatkan rekomendasi dari dokkes. 2. SIM sebelumnya namanya salah atau bagaimana pak/bu?
A321: 22 | B321: 1. Surat konfirmasi ETLE kok baru saya terima... padahal pelanggaran tertera pada tgl 27 Nov 2. Saya cek lewat online tidak bisa karena data tidak ditemukan 3. Di surat tertera paling lambat tgl 5 Des untuk konfirmasi, lah saya terima surat di tgl 12 Des 4. Ya, terima kasih. | C321: 1. Bisa dikonfirmasi sendiri ya pak/bu, di dalam ada tata cara konfirmasinya.
A322: 23 | B322: 1. "Selamat pagi, mohon informasi mengenai syarat perpanjangan SIM A dan lokasi pelayanan SIM keliling."2. "Apakah surat keterangan sehat bisa dari puskesmas?"3. "Berapa biaya perpanjangan SIM A?"4. "Saya bawa surat keterangan sehat dari puskesmas, namun ditolak oleh petugas tes kesehatan. Lokasi SIM keliling Pondok Tjandra."5. "Dari puskesmas, surat sehat berlaku 3 hari. Tapi petugas SIM keliling bilang harus tes di lokasi."6. "Ya, saya akan langsung tes di lokasi lain waktu." | C322: 1. "Untuk SIM keliling daerah Sidoarjo berada di sini: - LIPPO PLAZA - PONDOK TJANDRA - RAMAYANA KRIAN Jam Pelayanan: Senin-Kamis 08:00-12:00, Jumat-Sabtu 08:00-11:00 Persyaratan: - KTP asli - SIM asli - Fotokopi KTP 2 lembar - Fotokopi SIM 2 lembar - Surat Keterangan Sehat." 2. "Bisa." 3. "Untuk PNBP SIM A Panjang: 80.000, SIM C Panjang: 75.000. Biaya kesehatan dan psikologi di luar PNBP Polri." 4. "Mohon maaf, surat keterangan sehat dari puskesmas harus menyertakan keterangan masa berlaku. Pada surat sehat tersebut tidak ada keterangan tanggal berlaku, sehingga tidak bisa diproses." 5. "Mohon maaf, kedepannya agar disampaikan kepada petugas bahwa surat sehat dari puskesmas berlaku selama 3 hari dan diberi keterangan masa berlaku pada surat tersebut." 6. "Terima kasih atas pengertiannya, semoga ke depannya tidak terjadi kebingungannya lagi. Mohon maaf atas ketidaknyamanannya."
A323: 24 | B323: 1. "Halo, permisi izin bertanya untuk pembuatan SIM C baru, apakah bisa lewat SIM keliling? Terima kasih."2. "Kalau bikin SIM di Sidoarjo buka sampai tanggal berapa ya?" | C323: 1. "Tidak bisa, pak/bu, SIM keliling hanya untuk memperpanjang masa berlaku SIM A/C saja."2. "Untuk loket buka sampai pukul 12:00, pak/bu."
A324: 25 | B324: 1. "Selamat siang, mohon info pelayanan SIM keliling untuk wilayah Sidoarjo besok. Terima kasih atas perhatiannya." | C324: 1. "Untuk SIM keliling daerah Sidoarjo berada di sini, pak/bu: 1. LIPPO PLAZA 2. PONDOK TJANDRA 3. RAMAYANA KRIAN Jam pelayanan mulai pukul 08:00 - 12:00 di hari Senin sampai Kamis, dan pukul 08:00 - 11:00 pada hari Jumat dan Sabtu."
A325: 26 | B325: 1. "Selamat pagi bapak/ibu, mohon maaf sebelumnya mau bertanya u/ jadwal SIM keliling di Sidoarjo untuk hari Rabu tgl 18 Des besok apakah ada ya bapak/ibu? Sebelumnya terimakasih."2. "Apabila sudah melakukan pengajuan online digital Korlantas tetapi masih belum direspon, apakah bisa untuk diurus di SIM keliling ya?"3. "Lalu untuk keterangan sehat, diperbolehkan dari puskesmas?" | C325: 1. Untuk SIM keliling daerah Sidoarjo berada di sini Pak/Bu: - LIPPO PLAZA - PONDOK TJANDRA - RAMAYANA KRIAN Jam Pelayanan Mulai Pukul 08.00 - 12.00 di hari Senin sampai hari Kamis, bila hari Jumat dan Sabtu jam pelayanan dimulai pukul 08.00 - 11.00. 2. Bisa, monggo dicoba saja di SIM keliling kak. 3. Kalau sudah pembayaran/sudah menyelesaikan semua persyaratan di SIM online bisa ditunggu saja kak.
A326: 27 | B326: 1. PK polisi mau tanya biaya balik nama itu, berapa, mobil Innova. 2. Suami saya balik nama pakek jabut bendel, suratan Jombang, yg punya mobil sudah laporan kalau mobilnya sudah dijual, jadi kan balik nama. Sedangkan suami saya orang Mojokerto, kemarin lihat di Google katanya ada pemutihan ternyata hoax, gimana sih pak? Kami rakyat perlu dilayani secara baik. Saya marah-marah, masak PK balik nama disuruh bayar 15 juta, apa sudah gila dunia ini. Mohon pak dijelaskan, bapak sebagai pengayom masyarakat tolong dibantu. 3. PK tolong dijelaskan, butuh penjelasan. 4. Gimana PK, saya tunggu solusinya. 5. Tanggal 3 Desember 2024. 6. BPKB-nya kan di bank PK, suami saya nitip di bank. Pertama minta uang 6 juta, kalau pengen cepat harus bayar lagi 6 juta supaya cepat selesai. Tapi PK ujung-ujungnya minta tambah lagi uang 5 juta, gimana PK? Mobilnya milik orang Jombang, PK masak pindah ke Mojokerto sampai 15 juta, katanya akhir Desember ada pemutihan, cuma omong kosong belaka. Maaf PK polisi apabila saya berkata-kata salah, mohon maaf ya PK. 7. Kemarin saya lihat di Google sampai akhir tahun. 8. PK polisi apa nggak ada pemutihan, habisnya segitu banyak, kenapa PK balik nama beda kabupaten. 9. Jaminan PK. 10. Stres PK rasanya. Teman saya aja balik nama Banjarmasin pindah Mojokerto habis 9 juta, mobilnya Pajero itu PK, kok Innova sebanyak itu. 11. PK polisi apa nggak bisa bantu kami. 12. Ini PK polisi rinciannya. 13. Ini habis 11 jutaan, minta tambah lagi 5 juta, PK polisi. Waduh-waduh, ini apa bukan namanya pemerasan, PK polisi. 14. Kami ini orang desa PK, juga bukan orang yang berduit, kok tega. Mobilnya pun tahun 2014, iya kok tahun sekarang 2024 gitu. 15. PK polisi sekarang ada pemutihan, lihat di TikTok, apa benar PK? Juga buat SIM juga. Apa benar PK polisi. | C326: 1. Untuk pengurusan tanggal berapa pak/bu? 2. Mohon maaf ibu, untuk pemutihan berakhir di tanggal 30 November. 3. Berikut informasinya pak/bu. 4. Dapat informasi dari mana ya pak/bu? 5. Informasi bisa didapatkan dari sosmed RTMC Polda Jatim dan Ditlantas Polda Jatim. [Link Instagram] 6. Di bank itu sebagai apa ya pak/bu, jaminan atau bagaimana? 7. Coba ibu konfirmasi ke pihak banknya terlebih dahulu mengapa bisa jadi mahal seperti itu. 8. Setiap pembayaran pasti ada rincian/nota untuk pembayarannya pak/bu. 9. Bisa langsung ke Samsat Mojokerto, langsung ke bagian informasi pak/bu untuk lebih jelasnya. 10. Tidak benar pak/bu. 11. Pemutihan sudah berakhir pada tanggal 30 November.
... A389: 12 | B389: 1. Selamat siang kak mau tanya ? Utk pembuatan SKCK di Polda jatim bagi KTP luar daerah, bisa kak? 2. KTp sy kepulauan Masalembu, sy bekerja di Lab. Perikanan SBY. 3. Utk pemberkasan PPPK disyaratkan utk membuat SKCK.🙏 4. Mohon petunjuk kak?🙏 | C389: Siang mhn maaf kami tanyakan terlebih dahulu
A390: 13 | B390: Selamat siang Mohon informasi untuk pelayanan perpanjang SIM, jam operasional nya jam berapa? Sya warga kec. dawarblandong | C390: Kota mana ya pak/bu | E390: WHATSAPP | F390: =COUNTIF(#REF!,E390) -> 0 | H390: SAMSAT | I390: =COUNTIF(#REF!,H390) -> 0 | K390: REGIDENT | L390: =COUNTIF(#REF!,K390) -> 0
A391: 14 | B391: 1. Selamat malem kak2. Mw tanyak unk perpanjang SIM di Lippo apa hrs ambil nomor antrian dlu ya? 3. SIM saya terakhir tgl 8 Januari 4. Berarti besok bisa ya | C391: 1. Bisa langsung antri di tempat ya pak/bu 2. Bisa pak/bu | E391: FACEBOOK | F391: =COUNTIF(#REF!,E391) -> 0 | H391: SIM | I391: =COUNTIF(#REF!,H391) -> 0 | K391: GAKKUM | L391: =COUNTIF(#REF!,K391) -> 0
A392: 15 | B392: 1. Ndan mau tanya apakah bisa perpanjang SIM di SIM keliling sedangkan saya masih dalam proses SIM online presentasi masih 40% padahal sudah 9 jari prosesnya 2. Tapi masa berlaku SIM saya tgl 19 sedangkan sekarang tgl 9 kurang 10 hari masa berlaku SIM saya | C392: 1. Bila sudah melakukan registrasi sim online lebih baik menunggu untuk prosesnya hingga selesai pak/bu | E392: INSTAGRAM | F392: =COUNTIF(#REF!,E392) -> 0 | H392: LAKA | I392: =COUNTIF(#REF!,H392) -> 0 | K392: PJR | L392: =COUNTIF(#REF!,K392) -> 0
A393: 16 | B393: 1. Selamat Siang Bapak mau menanyakan informasi perpanjangan SIM C, utk di Ramayana Krian apa buka setiap hari? 2. Terima kasih banyak Pak/Ibu atas informasinya 🙏🏻🙏🏻 | C393: 1. Untuk Sim keliling daerah sidoarjo berada di sini pak/bu - LIPPO PLAZA - PONDOK TJANDRA - RAMAYANA KRIAN Jam Pelayanan Mulai Pukul 08.00 - 12.00 Di hari Senin sampai hari Kamis bila hari Jumat dan Sabtu jam pelayanan dimulai pukul 08.00 - 11.00 | E393: X/TWITTER | F393: =COUNTIF(#REF!,E393) -> 0 | H393: TILANG | I393: =COUNTIF(#REF!,H393) -> 0 | K393: KAMSEL | L393: =COUNTIF(#REF!,K393) -> 0
A394: 17 | B394: 1. Selamat Siang, Pak. Maaf mau tanya? SIM KELILING di Ramayana Krian, Selain tanggal 8 Januari. Tanggal brp saja ya, yg standby di Ramayana Krian?2. Apakah minggu depan juga ada? 3. Dan setiap hari apa, Standby di Ramayana Krian?? 4. Terima kasih 🙏🙏 | C394: 1. Untuk Sim keliling daerah Sidoarjo berada di sini pak/bu - LIPPO PLAZA - PONDOK TJANDRA - RAMAYANA KRIAN Jam Pelayanan Mulai Pukul 08.00 - 12.00 Di hari Senin sampai hari Kamis, bila hari Jumat dan Sabtu jam pelayanan dimulai pukul 08.00 - 11.00 | F394: =SUM(F390:F393) -> 0 | H394: LAIN-LAIN | I394: =COUNTIF(#REF!,H394) -> 0 | K394: LAIN-LAIN | L394: =COUNTIF(#REF!,K394) -> 0
A395: 18 | B395: Pak...tanya...rincian pajak 5 thunan apa aja ya...(ganti Plat nomor)..makasihbiayanya...Sugih Seger WarasMotor honda beat 2015Ok PakMatur nuwun 🙏🙏🙏2. Pak Bos tanya...Klo Plat W Gresik...ganti Plat 5 thnn di Sby..Apa bisa Pak ..Klo bisa...Mau ngurus di Samsat Manyar aja...biar gag Jauh2 ke GresikSugih Seger WarasMakasih...Saya tunggu jawabannya ya Pak... 🙏🙏🙏Siap...Terima Kasih Pak... 🙏🙏🙏 | C395: Info Layanan Bapenda Jatimbiaya PNBP stnk : Rp. 100.000plat nomor : 60.000untuk biaya pajak bisa cek di : https://info.dipendajatim.go.id/index.php?page=info_pkbterima kasih kembalitidak bisa pak, bila perpanjang 5 tahunan harus menuju ke samsat asal | I395: =SUM(H378:H382) -> 0
A396: 19 | B396: Bismillah. Mohon ijin. Traffic light Gebang Lingkar Timur Sidoarjo yang ke arah utara atau dari selatan mati. Lalu depan informa jalannya rusak. | C396: Terimakasih informasinyaBisa menuju ke Polsek terdekat pak/bu
A397: 20 | B397: Halo apakah besok sim kelilinh ada ya pak?Sudah Pak, SIM saya sudah slesai scara online, tdak jd bkin di sim,kelilinh, trimakssih | C397: Untuk Sim keliling daerah sidoarjo berada di sini pak/bu 1. LIPPO PLAZA 2. PONDOK TJANDRA 3. RAMAYANA KRIAN Jam Pelayanan Mulai Pukul 08.00 - 12.00 Di hari Senin sampai hari Kamis bila hari jum at dan sabtu jam pelayanan dimulai pukul 08.00 - 11.00
A398: 21 | B398: ndan tgl 05 apakah ada SIM keliling di pondok candraBerarti hari senin sampai jumat ada SIM klilingya Persyaratan apa saja yang dibawa untuk perpanjang SIM nya Matur nuwon infonya | C398: tanggal 5 hari minggu pelayanan tutup pakUntuk Sim keliling daerah sidoarjo berada di sini pak/bu1. LIPPO PLAZA2. PONDOK TJANDRA3. RAMAYANA KRIANJam Pelayanan Mulai Pukul 08.00 - 12.00 Di hari Senin sampai hari Kamis bila hari jum at dan sabtu jam pelayanan dimulai pukul 08.00 - 11.00ktp asli, sim lama, fotokopi sim dan ktp 2 kali
A399: 22 | B399: Maaf.. Untuk jadwal sim kelililing di Ramayana krian, hari jumat (17 Januari 2025 ) dan sabtu ( 18 Januari 2025 ) .. Terimakasih | C399: Untuk Sim keliling daerah sidoarjo berada di sini pak/bu 1. LIPPO PLAZA 2. PONDOK TJANDRA 3. RAMAYANA KRIAN Jam Pelayanan Mulai Pukul 08.00 - 12.00 Di hari Senin sampai hari Kamis bila hari jum at dan sabtu jam pelayanan dimulai pukul 08.00 - 11.00
A400: 23 | B400: Siang kak Dimas Narendra Kak mohon info dong berkas untuk buka blokir BPKB untuk mutasi kendaraan R4 | C400: mohon waktu
A401: 24 | B401: Selamat siang Pak/Bu. Mau bertanya, paman saya tgl 28 des perpanjangan sim C. Tp sampai sekarang blm selesai. Dan masih 40%. Kemungkinan kenapa ya pak bu?Iya kak, tp tgl 17 Januari expired simnya. Gimana kalau sampai tgl 17 belum jadi kak? Mohon bantuannya kak?M1553241228079ON A.n Ponidi Mohon segera diproses kak, expired 17 Januari 🥲Mohon dong kak, segera diproses 🙏 | C401: masih proses kak, dan antrian proses sesuai dengan kapan di daftarkan di aplikasinya jadi mohon ditunggu sajamohon maaf kak untuk antrian dari sim online sesuai urutan jadi kami tidak bisa membantu untuk memproses, dan tugas kami disini hanya untuk memberikan informasidan untuk sim yang terlewat/expired lebih dulu sebelum sim online selesai tidak masalah kak karena sudah di ajukan untuk perpanjangan sim online sebelum sim expired
A402: 25 | B402: siang kak mau taya kalo sim ktp surabya bisa gk byr di Sidoarjodyandradi samsat keliling yg Sidoarjoutuk surat keterangan sehat di tempat Ramayana krian ada gk kak | C402: bisa kak
A403: 26 | B403: Malam Syarat perpanjangan sim C apa saja 215486 Apa perlu surat keterangan sehat dan ngurus nya di rumah sakit mana? | C403: diperlukan pak/bu, untuk pengurusan bisa dilakukan di tempat sim keliling/sim cornen sudah tersedia untuk jasa tes kesehatan maupun tes psikologi
A404: 27 | B404: Selamat sore admin,Mhn informasi admin kalau mau urus perpanjangan sim A maupun C di sim keliling lippo plaza sidoarjo surat kesehatanya urus di lokasi atau bawa dari luar ya? | C404: ditempat perpanjangan sudah tersedia untuk tes kesehatan dan tes psikologi pak/bu
A405: 28 | B405: Kak kalau perpanjang sim dri sby ke sidoarjo alurnya gimana yApa bisa di sim keliling ?Persyaratannya apa saja | C405: bisa kakUntuk Sim keliling daerah sidoarjo berada di sini pak/bu 1. LIPPO PLAZA 2. PONDOK TJANDRA 3. RAMAYANA KRIAN Jam Pelayanan Mulai Pukul 08.00 - 12.00 Di hari Senin sampai hari Kamis bila hari jum at dan sabtu jam pelayanan dimulai pukul 08.00 - 11.00
A406: 29 | B406: Mau tanya sim saya mati 2 minggu apa bisa di perpanjang .??? Untuk area waru pondok candra . Terima kasih . Mohon di balas inboxnya | C406: tidak bisa pak/bu untuk sim mati diwajibkan untuk membuat sim baru
A407: 30 | B407: Assalamualaikum Min mau tanya untuk wilayah sidoarjo surat keterangan sehat dimana ya min? | C407: bisa didapatkan di tempat perpanjangan pak/bi
... A2366: 216 | B2366: 1. Selamat siang pak , mau tanya soal sim keliling /untuk perpanjangan Kalau tes kesehatan + tes psikologi, dilakukan, ditempat (Ramayana krian) atau bagaimana nggih?2. Berarti pas tes kesehatan,bisa ditempat (ramayana) nggih? 3. Kalau ngambil nomor antrian pas datang pagi² itu ya pak4. Sim saya mati tgl 10 bulan depan pak, misal perpanjangan H- berapa5. Siap pak, sy tunggu upgrade jadwalny di ig pak , terimakasih atas infonya pak | C2366: 1. untuk kesehatan bisa di tempat atau di klinik dan untuk psikologi bisa di lakukan di tempat kak2. betul kak3. bisa kak4. SIM Keliling di Sidoarjo tersedia di Lippo Plaza, Pondok Tjandra, dan Ramayana Krian dengan jam pelayanan: - Senin - Kamis: 08.00 - 12.00 - Jumat & Sabtu: 08.00 - 11.00
B2367: 1. info jadwal sim keliling | C2367: 1. SIM Keliling di Sidoarjo tersedia di Lippo Plaza, Pondok Tjandra, dan Ramayana Krian dengan jam pelayanan: - Senin - Kamis: 08.00 - 12.00 - Jumat & Sabtu: 08.00 - 11.00
B2368: 1. Selamat pagiUntuk perpanjang SIM A di Kahuripan nirwana,ada syarat kesehatan dokter SM psikologi,itu bisa dilakukan disana atau mencari sendiri sebelum perpanjangan ya?2. Jadi yg perlu disiapkan dr rumah apa aja kak?3. Oh ya untuk SIM habis tgl 11 kak,besok sudah bisa perpanjang kan ya?4. Kak yg di Kahuripan nirwana g ada ya?5. Diganti di Lippo?6.G perlu antri subuh kan kak?Sy di taman kakJauh kedua2nya7. Cuma sy nyari yg sepi kiranya,Krn bawa 2 bayi8. Tetep ambil antrian subuh kah?9. Bisa diinfo lokasi yg di pocan?Makasih kak infonya ❤️10. Sama 2 lansia dan 2 bayi 5 bulan 🤭Siap kak11. Iya kak,semoga g antri banyak besok 12. Makasih kak,met istirahat ❤️ | C2368: 1. selamat malam kak maaf tadi ada trobel sistem jadi lama balas nya2. untuk kesehatan sm psikologi ada di tempat kak3. itu kak syarat nya sim yg akan perpanjang dan ktp4. sudah bisa kak5. ada kak6. lippo dari polda kalau di kahuripan dari polresta sidoarjo7. kakak rumah nya dekat lippo apa kahuripan?8. bisa tinggal di pilih terdekat9. taman kalau ke pocan jauh kah kak?10. kalau sepi tidak nya itu kita belum tau ya kak11. karna tidak tentu untuk yg ngurus brpa banyak12. tidak harus kak13. kalau awal bulan seperti ini kebanyakan rame kak14. bawah foto copy ktp sm sim nya masing² 3 lembar kak biar tidak bingung cari foto copy lg15. ruko palm kaksama sama kak16. besok sendiri apa sm suami?17. saran saya di temani suami kak takut nya anak nya rewel pas saat tes psiko atau kesehatanatau bawa saudara18. oh ya kak alhamdulillah kalau ada kakek nenek nya yaa semoga kak terimakasih kak 🥰
A2369: 3 | B2369: 1. Kak mau tanya apakah besok pelayanan perpanjang SIM buka?2. siap makasih kak | C2369: 1. buka kak
A2370: 4 | B2370: 1. selamat malam | C2370: 1. malam kak
A2371: 5 | B2371: 1. info jadwal sim keliling besok kak | C2371: 1. SIM Keliling di Sidoarjo tersedia di Lippo Plaza, Pondok Tjandra, dan Ramayana Krian dengan jam pelayanan: - Senin - Kamis: 08.00 - 12.00 - Jumat & Sabtu: 08.00 - 11.002. sama sama kak
A2372: 28 | B2372: 1. pagi mohon info jadwal sim keliling sidoarjo | C2372: 1. SIM Keliling di Sidoarjo tersedia di Lippo Plaza, Pondok Tjandra, dan Ramayana Krian dengan jam pelayanan: - Senin - Kamis: 08.00 - 12.00 - Jumat & Sabtu: 08.00 - 11.002. sama sama kak
A2373: 1 | B2373: 1. Untuk perpanjangan SIM C di Lippo Plaza Sidoarjo, apakah masih perlu ambil nomor antrean seperti dulu? | C2373: 1. Tidak perlu, bisa langsung datang ke lokasi SIM Keliling di Lippo Plaza Sidoarjo.
A2374: 2 | B2374: 1. Terakhir buka untuk perpanjangan SIM tanggal berapa ya? Tadi ke Ramayana Krian sudah full kuotanya.2. Apakah besok ada pelayanan perpanjangan SIM keliling di Ramayana Krian? | C2374: 1. SIM Keliling di Sidoarjo tersedia di Lippo Plaza, Pondok Tjandra, dan Ramayana Krian dengan jam pelayanan: - Senin - Kamis: 08.00 - 12.00 - Jumat & Sabtu: 08.00 - 11.002. Ada, pelayanan SIM keliling tersedia setiap hari di Ramayana Krian.
A2375: 3 | B2375: 1. Apakah besok layanan perpanjangan SIM keliling di Ramayana Krian Sidoarjo buka?2. Apakah hari Rabu masih buka juga? | C2375: 1. Buka, layanan SIM keliling di Ramayana Krian tetap beroperasi.2. Hari Rabu juga buka.
A2376: 4 | B2376: 1. Jadwal SIM keliling di Sidoarjo minggu ini?2. Apakah perpanjangan SIM bisa dilakukan 1 minggu sebelum tanggal kedaluwarsa?3. Apakah besok (Selasa) layanan SIM keliling di Lippo Plaza buka? | C2376: 1. SIM Keliling di Sidoarjo tersedia di Lippo Plaza, Pondok Tjandra, dan Ramayana Krian dengan jam pelayanan: - Senin - Kamis: 08.00 - 12.00 - Jumat & Sabtu: 08.00 - 11.002. Bisa, perpanjangan dapat dilakukan 1 minggu sebelum tanggal expired.3. Buka, layanan SIM keliling di Lippo Plaza tetap beroperasi pada hari Selasa.
A2377: 5 | B2377: 1. SIM saya habis tanggal 17 bulan ini, perpanjangnya bisa mulai tanggal berapa?2. Apakah bisa seminggu sebelumnya?3. Jadwal SIM keliling di Ramayana Krian hari apa saja?4. Selain Instagram, bisa lihat jadwal dari mana lagi? | C2377: 1. Bisa langsung perpanjang sebelum tanggal kedaluwarsa, termasuk seminggu sebelumnya.2. Jadwal SIM Keliling Ramayana Krian:Senin - Kamis: 08.00 - 12.00Jumat & Sabtu: 08.00 - 11.003. Jadwal layanan juga dapat dilihat melalui Facebook selain Instagram.
A2378: 6 | B2378: 1. Apakah ada jadwal SIM Keliling di Surabaya?2. Apa saja persyaratan yang harus dibawa untuk perpanjangan SIM? | C2378: 1. Belum ada informasi jadwal SIM Keliling untuk Surabaya.2. Persyaratan Perpanjangan SIM:KTP asliSIM asliFotokopi KTP (2 lembar)Fotokopi SIM (2 lembar)Surat Keterangan Sehat (bisa didapatkan di lokasi perpanjangan)
A2379: 7 | B2379: 1. Mohon infoApakah sudah ada program pemutihan pajak kendaraan Terimakasih infonya | C2379: 1. sementara belum ada kakak
A2380: 8 | B2380: 1. Selamat sore Mau tanya SIM keliling untuk area surabaya dimana saja buat selasa besok??? 🙏🙏🙏2. Terima kasih infonya🙏🙏🙏3. Kalo seminggu sebelum jatuh tempo tgl SIM nya bisa ya, Soalnya habisnya pas tgl libur | C2380: 1. belum ada info kak daerah sby2. SIM Keliling di Sidoarjo tersedia di Lippo Plaza, Pondok Tjandra, dan Ramayana Krian dengan jam pelayanan: - Senin - Kamis: 08.00 - 12.00 - Jumat & Sabtu: 08.00 - 11.003. bisa kak
... A2449: 4 | B2449: 1. Selamat siang, apakah ada info terkait perpanjangan di SIM Keliling di Sidoarjo ?2. KTP Luar Sidoarjo apakah bisa?3. Terima kasih infonya admin | C2449: 1. SIM Keliling di Sidoarjo tersedia di Lippo Plaza, Pondok Tjandra, dan Ramayana Krian dengan jam pelayanan: - Senin - Kamis: 08.00 - 12.00 - Jumat & Sabtu: 08.00 - 11.002. bisa kak

Sheet JENIS
F1: SUBDIT
B2: JENIS | D2: PERTANYAAN | F2: REGIDENT
B3: WHATSAPP | D3: SAMSAT | F3: GAKKUM
B4: FACEBOOK | D4: SIM | F4: PJR
B5: INSTAGRAM | D5: LAKA | F5: KAMSEL
B6: TIKTOK | D6: ETLE | F6: LAIN-LAIN
D7: LAIN-LAIN
D8: STNK
D9: BPKB

Sheet Sheet4
B3: WHATSAPP | C3: 22 | G3: SAMSAT | H3: 12 | L3: REGIDENT | M3: 29 | Q3: WHATSAPP | R3: 128 | U3: SAMSAT | V3: 7 | Z3: REGIDENT | AA3: 145
B4: FACEBOOK | C4: 4 | G4: SIM | H4: 20 | L4: GAKKUM | M4: 5 | Q4: FACEBOOK | R4: 3 | U4: SIM | V4: 138 | Z4: GAKKUM | AA4: 4
B5: INSTAGRAM | C5: 10 | G5: LAKA | H5: 0 | L5: PJR | M5: 0 | Q5: INSTAGRAM | R5: 25 | U5: LAKA | V5: 0 | Z5: PJR | AA5: =COUNTIF(REKAP!$F$428:$F$444,Z5) -> 0
B6: X/TWITTER | C6: =COUNTIF(REKAP!$C$428:$C$444,B6) -> 0 | G6: TILANG | H6: 4 | L6: KAMSEL | M6: 0 | Q6: X/TWITTER | R6: =COUNTIF(REKAP!$C$428:$C$444,Q6) -> 0 | U6: TILANG | V6: 4 | Z6: KAMSEL | AA6: 0
C7: =SUM(C3:C6) -> 36 | G7: LAIN-LAIN | H7: 0 | L7: LAIN-LAIN | M7: 0 | R7: =SUM(R3:R6) -> 156 | U7: LAIN-LAIN | V7: 9 | Z7: LAIN-LAIN | AA7: 9
H8: =SUM(H3:H7) -> 36 | M8: =SUM(M3:M7) -> 34 | V8: =SUM(V3:V7) -> 158 | AA8: =SUM(AA3:AA7) -> 158
A34: JAN - MEI
A35: WHATSAPP | B35: 177 | D35: SAMSAT | E35: 23 | G35: REGIDENT | H35: 188
A36: FACEBOOK | B36: 20 | D36: SIM | E36: 165 | G36: GAKKUM | H36: 17
A37: INSTAGRAM | B37: =COUNTIF(REKAP!$C$375:$C$523,A37) -> 18 | D37: LAKA | E37: =COUNTIF(REKAP!$E$375:$E$523,D37) -> 0 | G37: PJR | H37: =COUNTIF(REKAP!$F$375:$F$523,G37) -> 0
A38: X/TWITTER | B38: =COUNTIF(REKAP!$C$375:$C$523,A38) -> 0 | D38: TILANG | E38: 17 | G38: KAMSEL | H38: 0
B39: =SUM(B35:B38) -> 215 | D39: LAIN-LAIN | E39: 19 | G39: LAIN-LAIN | H39: 19
E40: =SUM(E35:E39) -> 224 | H40: =SUM(H35:H39) -> 224

Sheet Sheet5
A1: NO | B1: TANGGAL | C1: MEDIA ADUAN | D1: NAMA / NOMOR | E1: JENIS | F1: SUBDIT | G1: PERTANYAAN | H1: JAWABAN
A2: 1 | B2: 46024 | C2: WHATSAPP | D2: +62 856-7649-513 | E2: SIM | F2: REGIDENT | G2: 1. Saya ingin bertanya tentang ... perpanjang SIM hari Jumat 2 Desember apakah sudah beroperasi kembali SIM keliling Ramayana Ciplaz/terminal pasar Porong. Terimakasih 2. Baik saya tunggu informasi 3. Min, bagaimana? apakah hari ini SIM keliling sudah beroperasi kembali di Ramayana Ciplaz Sidoarjo? terimakasih | H2: 1. mohon waktu ya kak saya tanyakan untuk wilayah sidoarjo 2. sdh kak
A3: 2 | B3: 46024 | C3: WHATSAPP | D3: +62 899-8989-602 | E3: SIM | F3: REGIDENT | G3: 1. Selamat malam, Besok SIM keliling Sidoarjo buka ga min? | H3: 1. buka kak
A4: 3 | B4: 46024 | C4: WHATSAPP | D4: +62 812-3598-421 | E4: SAMSAT | F4: REGIDENT | G4: 1. Mohon info, saya akan balik nama kendaraan R4 utk bayar pajak, tp ternyata di samsat asal (Gresik) infonya perlu buka blokir ke Polda Jatim tp sebelumnya ke BCA Finance dulu. Stl ke BCA, infonya tidak ada data plat no kendaraan saya di data BCA. Lalu bagaimana saya mengurus buka blokir ke Polda Jatim kalau surat pengantar dari Bank tidak ada ? 2. Baik, terima kasih infonya 3. Mohon info dokumen apa saja yang perlu dibawa ? 4. surat keterangan dri leasing ------> ini yg nggak ada, saya minta ke BCA Finance sesuai info dr Samsat Gresik infonya dari BCA Finance nggak ada Lalu bagaimana ? BPKB, STNK, Kuitansi pembelian ada semua Cek fisik kendaraan, mesin, rangka di Samsat Gresik juga sdh ada | H4: 1. mnta data di polda gedung rtmc bagian blokir 2. sma2 kak 3. surat keterangan dri leasing,bpkb asli,stnk asli 4. mnta data di bagian blokir polda gedung rtmc,untuk mnta data ikut leasing bca mna 5. untuk kendaraan kakak 6. betul kak
A5: 4 | B5: 46024 | C5: WHATSAPP | D5: +62 822-3130-3326 | E5: SIM | F5: REGIDENT | G5: 1. Saya ingin bertanya tentang perpanjangan SIM hari ini apa bisa 2. Expired kuu tgl 26 Januari apa bisa ? | H5: 1. bisa bsk kak jm 8.00 - 12.00 wib 2. bisa H-3 kak untuk perpanjangan
A6: 5 | B6: 46024 | C6: WHATSAPP | D6: +62 895-3417-64793 | E6: SIM | F6: REGIDENT | G6: 1. halo ka untuk pelayanan perpanjangan sim di taman bungkul apakah ada ya? bukanya jam berapa kalo boleh tau? | H6: 1. program simanis di tmn bungkul jumat,sabtu jm18.00 - 21.00 wib
A7: 1 | B7: 46026 | C7: WHATSAPP | D7: +62 857-3343-6300 | E7: SAMSAT | F7: REGIDENT | G7: 1. Selamat siang, Admin. Mohon izin bertanya terkait prosedur permohonan Nomor Registrasi Kendaraan Bermotor (NRKB) Pilihan atau pelat nomor cantik. Apa saja persyaratan dokumen yang harus disiapkan dan bagaimana alur pengurusannya? Terima kasih atas informasinya. 2. Mohon informasinya mengenai jadwal jam operasional layanan di kantor RTMC. Pada hari apa saja layanan tersebut tersedia. Terima kasih 3. Baik, Terima kasih atas informasinya🙏🏻 | H7: 1. siang juga kak.bisa lsg dtg ke polda gedung rtmc,sie stnk bawa bpkb asli,stnk asli,ktp asli di fto copy 2rangkap 2. senin - kamis 08.00 - 12.00 jumat - sabtu 08.00 - 11.00 3. sma2 kak
A8: 2 | B8: 46026 | C8: WHATSAPP | D8: +62 857-2118-9991 | E8: SAMSAT | F8: REGIDENT | G8: 1. Maaf mau bertanya, untuk pengurusan mutasi masuk kendaraan R2. Apakah hari Sabtu besok membuka layanan ? Serta persyaratan yg d bawa apa saja ya? Karena sebelumnya saya dari samsat tujuan d minta ke Polda Jatim. Apakah perlu membawakan kendraaan R2 nya ke Polda / cukup berkasnya saja ? 2. Ini saya perlu bawa kendaraan R2 nya atau cukup berkasnya saja ya ? Karena kemarin dari Samsat Talangagung, di minta ke polda setelah cek fisik 3. Baik, setelah verifikasi online nanti saya masukan kembali berkasnya ke Samsat Talangagung atau pencetakan STNK dn TNKB di Rtmc ? 4. Kak maaf satu lagi, Kendaraannya ga perlu di bawa ya? | H8: 1. buka kak untuk sabtu bsk jm8.00 - 11.00 wib 2. betul kak bawa berkas ke polda gedung rtmc sie stnk dan sie bpkb untuk proses kroscek dan verifikasi online 3. setelah proses di polda selesai baru di bawa ke samsat tujuan 4. sama2 kak 5. klau di polda tidak perlu kak 6. sma2 kak
A9: 3 | B9: 46026 | C9: WHATSAPP | D9: +62 895-3649-35567 | E9: SIM | F9: REGIDENT | G9: 1. Saya mau buat laporan atas pelaku penipuan di daerah gubeng sini musti ke polsek gubeng atau polres ya? 2. Baik, pengaduan atau lapor gitu sore masih bisa ya? | H9: 1. bisa di polres kak 2. bisa kak
A10: 1 | B10: 46027 | C10: WHATSAPP | D10: +62 856-5582-9982 | E10: SIM | F10: REGIDENT | G10: 1. Pagi kak 2. Persyaratan perpanjang sim apa aja 3. kalo di sim keliling area sidoarjo ada dimana kak 4. Untuk yg di lippo itu tutupnya jam brapa kak untuk sim cornernya 5. Pakai no antrian kah kak 6. Kalo yg di pondok candra itu di sebelah mananya pak | H10: 1. selamat pagi juga 2. foto copy ktp 3 lembar (ktp asli di bawa), foto copy sim 3 lembar (sim asli di bawa), untuk area sidoarjo ada di ramayana ciplas, 3. sampai jam 12.00 4. BETULA PAKAI ANTRIAN BAPAK 5. DI RUKO PALM BAPAK, ATAU SEBELAH TIMURNYA GIANT YANG SUDAH TUTUP
A11: 2 | B11: 46027 | C11: WHATSAPP | D11: +62 877-0288-1300 | E11: TILANG | F11: GAKKUM | G11: 1. Selamat pagi, RTMC Polda Jatim. Saya ingin bertanya mengenai pengurusan ganti stnk 5 tahunan di samsat sidoarjo, tapi kata pihak samsat bahwa kendaraan saya blokir etle polda , dan harus buka blokir di polda jatim, sedangkan saya tidak menerima sama sekali surat tilang untuk kendaaraan saya dan saya cek online data kendaraan saya memang tidak diketemukan pelanggaran. Mohon bantuan informasi nya terimakasih.🙏🏾 | H11: 1. bisa langsung konfirmasi di gedung pw polda jatim kak
A12: 3 | B12: 46027 | C12: WHATSAPP | D12: +62 852-3626-6344 | E12: TILANG | F12: GAKKUM | G12: 1. Saya ingin bertanya tentang cek etle untuk wilayah jawa timur | H12: 1. silakan datang ke polres / samsat terdekat
A13: 4 | B13: 46027 | C13: WHATSAPP | D13: +62 838-3068-2807 | E13: SAMSAT | F13: REGIDENT | G13: 1. Assalamu'alaikum pagi... Maaf, Samsat hari ini buka sampai jam brp?? 2. Klo kecamatan Sukodono mau ganti plat harus ke Samsat Krian kah??? Ap bisa klo di Samsat Sidoarjo Cemeng 3. Oh iya,,, ini berarti sy bayar pajak dan ganti plat 5 tahunan bisa di Samsat Sidoarjo Cemeng nggih🙏 4. Ini sy ke Samsat krian katanya ganti plat pindah ke trosobo 5. Bisa share alamat yg di trosobo | H13: 1. waalikumksalam, yan sampai jam 13.00 2. tidak bisa harus ke samsat asaL 3. jembatan timbang milik dishub /citra harmoni trosobo
... A175: 2 | B175: 46126 | C175: WHATSAPP | D175: 089677987686 | E175: TILANG | F175: GAKKUM | G175: 1. sudah mengisi data di web tapi belum dapat blangko via sms 2. baik pak | H175: 1. Ditunggu konfirmasi selanjut nya pak, kami sarankan untuk konfirmasi langsung ke Unit gakkum Polres
B176: 46128 | C176: WHATSAPP | D176: +62 811-3070-2826 | E176: TILANG | F176: GAKKUM | G176: 1. Nama: Rizki wahyu. Alamat: Wonorejo 4/31 surabaya. Informasi: Pengecekan apakah kena tilang etle. Saya cek di web error. | H176: 1. Untuk surat tilangnya dari mana bu? Mohon maaf untuk konfirmasi Etle masih ada perbaikan jaringan. 2. mohon waktu. silakan di byr untuk no briva nya sdh terlampir kak. 3. m banking bri. bisa lsg ke kcp bri kak. m bangking bri virtual accaount atau datang ke kcp bri terdekat.
A177: 1 | B177: 46128 | C177: WHATSAPP | D177: +62 822-6558-9819 | E177: SAMSAT | F177: REGIDENT | G177: 1. Nama: Luki Wahyuning T. Alamat: Tulungagung. Informasi: Izin tanya, jika pengambilan surat keterangan NRKB pilihan melewati/setelah tanggal yg tertera pada resi apakah diperbolehkan ya ? 2. Untuk pengambilan jika dikuasakan, apa saja persyaratan yg dibawa kak ? tidak perlu membawa bpkb dan stnk asli ya 3. Mohon info jam operasional kak | H177: 1. bisa diambil dan tidak apa apa kakak. 2. bisa melampirkan surat kuasa bertanda tangan diatas materai 10.000 dengan membawa ktp asli pemberi dan penerima kuasa. stnk asli di sertakan kakak. 3. Senin sd Sabtu Pukul 08.00 sd 13.00 Wib
A178: 2 | B178: 46128 | C178: WHATSAPP | D178: +62 822-5765-2986 | E178: TILANG | F178: GAKKUM | G178: 1. Nama: Eko Hidayat. Alamat: Benowo pasar rt re 01/01. Informasi: Mau buka blokir ETLE tidak bisa. Di suruh kembali lagi besok. Apakah aplikasi ETLE nya sudah bisa di gunakan? 2. Gak ada solusi kah kak? Kembali lagi seperti kemarin. 2 hari absen kerja. | H178: 1. halo kk terima kasih sdh menunggu untuk jaringan masih trobel besok bisa d proses seperti semula. 2. siap kk minta maaf ia kk insya ALLAH besok sdh bisa. 3. Mohon maaf atas ketidaknyamanannya.
A179: 1 | B179: 46128 | C179: WHATSAPP | D179: +62 878-5808-6000 | E179: TILANG | F179: GAKKUM | G179: 1. Nama: michael. Alamat: Jl. Pandean II/52. Informasi: tidak bisa bayar pajak mobil karena infonya ada tilang. 2. Hari ini sudah bisa ? Kemarin saya dari sana tapi infonya sistem masih error. Lokasi: Polda Jatim, jalan ahmad yani. | H179: 1. Silahkan di konfirmasi ke pusat pelayanan Etle terdekat, Polres atau Polda. 2. lokasi dimana kakak.
A180: 2 | B180: 46128 | C180: WHATSAPP | D180: +62 895-1590-0725 | E180: SIM | F180: REGIDENT | G180: 1. Mohon maaf mau tanya 剌 Untuk waktu SIM diterbitkan & masa berlaku SIM itu diisi sesuai yg tertera di SIM lama kah? | H180: 1. sesuai tanggal cetak terakhir yang ada di sim kakak
A181: 3 | B181: 46128 | C181: WHATSAPP | D181: +62 822-3421-0313 | E181: SIM | F181: REGIDENT | G181: 1. Nama: Gamma. Alamat: Bluru Kidul. Informasi/pengaduan: Untuk perpanjangan sim orang tua kandung | H181: apakah boleh dilakukan sang anak dengan surat kuasa dari orang tua nya ?
A182: 1 | B182: 46129 | C182: WHATSAPP | D182: +62 897-9799-904 | E182: TILANG | F182: GAKKUM | G182: 1. Nama : david. Alamat : pogot 10/19. Informasi/pengaduan : ETLE. Saya mau tnya kan kode referensi etle ,saya mau bayar lewat online pak 2. L4196CBC 3. Blum saya perbaiki simnya (masa berlaku mati) | H182: 1. bisa di fto stnk nya. bisa di ketik ulang nopol nya 2. Ijin pak pelanggarnya belum konfirmasi mgkn bisa dikirimkan simnya pak kami bantu konfirmasi dari sini. bisa di fto sim 3. masa berlaku sim sdh mati. bisa di fto sim terbaru. silakan di perbarui sim nya kak 4. saya confirm dlu ke operator nya. Ijin pak no briva dan no tilangnya Nopol L4196CBC
A183: 2 | B183: 46129 | C183: WHATSAPP | D183: +62 878-5392-1505 | E183: SIM | F183: REGIDENT | G183: 1. Nama : Andy. Alamat: jalan rambutan 7 He 06, pondok candra, Sidoarjo. Informasi: menanyakan layanan SIM keliling terdekat dari Pondok Candra Indah Sidoarjo, dan persyaratan dokumennya. 2. Mau tanya hari Sabtu apakah ada perpanjangan SIM keliling di pondok candra Sidoarjo? Kalau iya dari jam berapa-berapa ya? | H183: 1. ktp,sim asli di fto copy 3rangkap,tes sehat dan psikotes di sediakan di tkp
A184: 3 | B184: 46129 | C184: WHATSAPP | D184: +62 822-3481-9676 | E184: TILANG | F184: GAKKUM | G184: 1. Nama : marpuah. Alamat : dan. Buntut rt 04 rw08 tirtobinangun kab nganjuk. Informasi/pengaduan : cek data etle. Selamat siang saya mau cek data etle, karena STNK terblokir. 2. Tidak ada surat, hnya di beritahu samsat kalau ada etle, dan STNK diblokir. 3. Apakah setelah bayar denda STNK tidak lagi diblokir? Karena butuh untuk pengurusan pajak 5 tahunan. Cara bayarnya gimana ya. 4. Data tidak ditemukan (pada web kejaksaan). | H184: 1. bisa di fto surat etle nya. 2. setelah di byr lsg ke samsat menunjukan bukti byr nya. nanti untuk blokir terbuka. 3. https://tilang.kejaksaan.go.id masukan no reg tilang. 4. bisa di kirim fto sim.
A185: 1 | B185: 46129 | C185: WHATSAPP | D185: +62 823-3554-1927 | E185: SIM | F185: REGIDENT | G185: 1. Nama : Dani. Alamat : Jl. Medayu Utara XXXI no. 4 Rungkut - Surabaya. Informasi/pengaduan : Info Perpanjang SIM / SIM KELILING. 2. Sabtu buka kah kak? | H185: 1. bisa di yakaya kak. 2. betul kak. 3. buka kak jm08.00 - 12.00 wib
A186: 2 | B186: 46129 | C186: WHATSAPP | D186: +62 813-3612-5956 | E186: TILANG | F186: GAKKUM | G186: 1. Nama : Rudi s. Alamat : Pandegiling tengah 62. Informasi : etle surabaya. 2. L 1276 VG. 3. May minta info etle pak. Minta nomor tilang nya pak. Soal nya Surat nya hilang pak. 4. Stnk nya di rumah saya posisi di kejaksaan pak. | H186: 1. ada yang bisa dibantu kak. 2. siap kk ada yg bisa kami bantu kk. 3. stnk jenengan foto kk. 4. mohon waktu.
A187: 3 | B187: 46129 | C187: WHATSAPP | D187: +62 881-6264-375 | E187: SAMSAT | F187: REGIDENT | G187: 1. Nama: cholis yudianto. Alamat: bukit lawang indah blok u 2 lawang malang. Informasi: tidak bisa bayar stnk tahunan online karena ada blokir etle tapi cek tidak ada pelanggaran. 2. kalau ada etilang saya tidak ada surat nya tidak ada email nya saya juga tidak bisa cek online juga , bayar tilang pun tidak bisa secara online karena tidak ada data nya main blokir saja jadinya. 3. No berkas tilang saya berapa ? bisa dikasih tau. 4. Salah mobil saya warna merah. Bukan truk. 5. Tolong dibantu biar saya bisa perpanjang stnk saya secara online. | H187: 1. bisa di fto stnk nya. kami cek ke operator etle. 2. kami cek dlu untuk blokir nya. 3. Cek pak apa benar. apa benar untuk kendaraan nya. 4. bisa di fto kendaraan tampak depan dan belakang. 5. mohon waktu kami koordinasikan dlu untuk blokir nya. 6. silakan sdh terbuka untuk blokirnya. bisa di byr pjk nya.
A188: 1 | B188: 46129 | C188: WHATSAPP | D188: +62 823-3740-5543 | E188: TILANG | F188: GAKKUM | G188: 1. Nama: Octavan A. Alamat: kmp jagalan timur, kwanyar, bangkalan. Informasi: mau tanya, ini kendaraan mobil atas nama ibu saya mau perpanjang 5 tahunan, namun status kendaraan diblokir akibat etle surabaya, nah lantas apa yang harus dilakukan untuk membuka blokirna tersebut.. 2. Mau tanya apbila terkena tileng elektronik, namun tidak ddapat surat etle nya itu, ngeceknya dmn ? 3. Misalnya, terkena etle di sby, namun motornya itu domisili bangkalan, apa bisa cek di samsat bangkalan? | H188: 1. Bisa di fto surat etle nya kak. 2. di samsat terdekat loket blokir kak. 3. bisa kak. ke polres bagian gakkum lantas loket etle juga bisa kak.
... A300: 9 | B300: 46153 | C300: WHATSAPP | D300: +62 857-9134-7005 | E300: TILANG | F300: GAKKUM | G300: 1. Nama: Ishaq Yusron Akhsani. Alamat: Meri, Kranggan, Kota Mojokerto. 2. Permasalahan: Kendala teknis konfirmasi ETLE (No. Ref: 695-1F0C8-S1403SM) melalui web yang sempat error. Pelapor mempertanyakan status konfirmasi karena memegang surat fisik namun sempat diinformasikan data tidak ada oleh petugas. | H300: 1. Melakukan verifikasi ulang menggunakan foto STNK, SIM, dan surat fisik ETLE. 2. Menjelaskan bahwa nomor BRIVA berlaku 3 hari dan dapat dibayar via VA atau KCP BRI. 3. Mengarahkan pelapor untuk mengecek status konfirmasi dan blanko tilang secara mandiri melalui portal https://etilang.polri.go.id/.
A301: / | B301: 46154 | C301: WHATSAPP | D301: +62 812-1719-6308 | E301: SIM | F301: REGIDENT | G301: 1. Nama: Anggi Putra. Alamat: Anggaswangi, Sukodono. Informasi: Menanyakan kembali kepastian lokasi pelayanan SIM Keliling yang beroperasi pada hari ini (12 Mei 2026). | H301: 1. Menginformasikan lokasi SIM Keliling yang aktif hari ini berada di Pondok Tjandra, Kecamatan Sukodono, dan Ramayana Krian.
A302: 2 | B302: 46154 | C302: WHATSAPP | D302: +62 895-2316-9044 | E302: SIM | F302: REGIDENT | G302: 1. Menanyakan ketersediaan dan jadwal operasional SIM Keliling di Ciplaz Ramayana Sidoarjo. | H302: 1. Mengonfirmasi ketersediaan layanan di Ramayana Krian dan Ciplaz. 2. Menjelaskan jadwal operasional Senin s.d. Sabtu (kecuali hari Minggu dan tanggal merah) pukul 08.00 s.d. 12.00 WIB.
A303: 3 | B303: 46154 | C303: WHATSAPP | D303: +62 877-0276-6747 | E303: SIM | F303: REGIDENT | G303: 1. Nama: Angga Pahlevi. Alamat: Tanggulangin, Sidoarjo. 2. Informasi: Menanyakan lokasi SIM Keliling Sidoarjo, ketersediaan jadwal hari Sabtu/Minggu (karena kerja di hari kerja), serta status layanan di Lippo Mall/MPP Sidoarjo. | H303: 1. Menginformasikan lokasi aktif di Pondok Tjandra, Kec. Sukodono, dan Ramayana Krian. 2. Menjelaskan hari Minggu libur, namun hari Sabtu tetap buka pukul 08.00 s.d. 13.00 WIB. 3. Mengklarifikasi bahwa layanan di Lippo Mall sudah tidak ada.
A304: 4 | B304: 46154 | C304: TIKTOK | D304: Eci Naura | E304: SIM | F304: REGIDENT | G304: 1. Pelayanan SIM di Kecamatan Sukodono masih ada? 2. Kalau SIM mati sudah 2 tahun perpanjangannya berapa ongkosnya? | H304: 1. Masih 2. SIM yang telah habis masa berlakunya tidak dapat diperpanjang dan wajib membuat SIM baru
A305: 5 | B305: 46154 | C305: TIKTOK | D305: Keiko Traveling | E305: LAIN-LAIN | F305: GAKKUM | G305: 1. Pak tolong ditindak konten akun Tiktok Blackout dijalan tol. terimakasihj | H305: 1. Terimakasih atas informasinya, akan kami tindak lanjuti
A306: 6 | B306: 46154 | C306: TIKTOK | D306: AllisaS | E306: SIM | F306: REGIDENT | G306: 1. Perpanjang SIM di Kecamatan Sukodono apa masih ada? 2. Apa saja persyaratannya? | H306: 1. Masih ada dari senin - Sabtu 2. Membawa KTP dan SIM yang akan diperpanjang
A307: 7 | B307: 46154 | C307: TIKTOK | D307: ekoprasetya.id | E307: LAIN-LAIN | F307: LAIN-LAIN | G307: 1. Tolong pak ada pelanggar pengendara sepeda motor masuk ke jalur jembtan Suramadu malam malam kejadiannya | H307: 1. Terimakasih atas informasinya, akan kami tindak lanjuti
A308: 8 | B308: 46154 | C308: INSTAGRAM | D308: Murni Indriani | E308: SIM | F308: REGIDENT | G308: 1. Aplikasi untuk perpanjang SIM online apa? | H308: 1. Digital Korlantas Polri
A309: 9 | B309: 46154 | C309: WHATSAPP | D309: +62 822-3405-0917 | E309: SAMSAT | F309: REGIDENT | G309: 1. Nama: Adri Kurniawan. Alamat: Rungkut, Surabaya. 2. Informasi: Menanyakan status progres penerbitan BPKB pengganti (duplikat) dikarenakan dokumen asli hilang dan estimasi waktu penyelesaiannya. | H309: 1. Mengonfirmasi bahwa petugas akan menghubungi via WhatsApp jika BPKB sudah selesai. 2. Memberikan edukasi terkait estimasi waktu penerbitan BPKB duplikat yang membutuhkan waktu sekitar 6 bulan hingga 1 tahun.
A310: 1 | B310: 46155 | C310: WHATSAPP | D310: +62 812-3384-3287 | E310: SIM | F310: REGIDENT | G310: 1. Menanyakan ketersediaan layanan dan jadwal operasional SIM Keliling di wilayah Pondok Tjandra, Sidoarjo. | H310: 1. Mengonfirmasi ketersediaan layanan di Ruko Palm Pondok Tjandra. 2. Menginformasikan lokasi SIM Keliling Sidoarjo lainnya (Kec. Sukodono, Ramayana Krian, dan Ramayana Ciplaz) dengan jam operasional Senin-Sabtu pukul 08.00 s.d. 12.00 WIB.
A311: 2 | B311: 46155 | C311: WHATSAPP | D311: +62 813-3390-7553 | E311: TILANG | F311: GAKKUM | G311: 1. Nama: Agung. Alamat: Ngasem, Kediri. 2. Informasi: Kehilangan berkas surat ETLE dan ingin mengetahui nomor referensi untuk kendaraan AG 1127 GM (pelanggaran di Surabaya). | H311: 1. Meminta data identitas kendaraan (No. Rangka & No. Mesin) untuk pengecekan. 2. Menginformasikan terdapat 3 pelanggaran pada nopol tersebut. 3. Mengarahkan pelapor untuk mengecek detail data secara mandiri melalui portal resmi https://konfirmasi-etle.polri.go.id/cek-data.
A312: 3 | B312: 46155 | C312: WHATSAPP | D312: +62 822-3405-0917 | E312: SAMSAT | F312: REGIDENT | G312: 1. Nama: Adri Kurniawan. Alamat: Rungkut, Surabaya. 2. Informasi: Menanyakan status progres penerbitan BPKB pengganti (duplikat) dikarenakan dokumen asli hilang dan estimasi waktu penyelesaiannya. | H312: 1. Mengonfirmasi bahwa petugas akan menghubungi via WhatsApp jika BPKB sudah selesai. 2. Memberikan edukasi terkait estimasi waktu penerbitan BPKB duplikat yang membutuhkan waktu sekitar 6 bulan hingga 1 tahun.
A313: 4 | B313: 46155 | C313: WHATSAPP | D313: +62 878-1234-4555 | E313: SIM | F313: REGIDENT | G313: 1. Nama: Dhika Pramantya. Alamat: Waru, Sidoarjo. 2. Informasi: Menanyakan saran waktu terbaik untuk perpanjangan SIM yang habis pada hari Senin (18 Mei 2026), apakah sebaiknya hari Sabtu atau tetap di hari Senin mengingat hari Minggu layanan libur. | H313: 1. Menyarankan pemohon untuk melakukan perpanjangan pada hari Sabtu sebagai langkah antisipasi, namun tetap mengonfirmasi bahwa hari Senin pun masih bisa dilakukan selama belum melewati masa berlaku.
... A1354: 6 | B1354: 46286 | C1354: WHATSAPP | D1354: Uliful Fuadah 6281252150032 | E1354: LAIN-LAIN | F1354: LAIN-LAIN | G1354: Menyapa petugas layanan ("Selamat siang") untuk memulai interaksi atau menyampaikan pengaduan kepada pihak kepolisian. | H1354: Petugas menyambut sapaan pelapor dengan respons awal berupa sapaan balik dan tawaran bantuan ("Halo, terima kasih sudah menghubungi kami. Ada yang bisa dibantu?").
